Workbook

Sheet Dashboard
A1: Renewable Energy Tender Tracker
A3: Workbook foundation with agency master, tender database, status tracking, and update-control area
A4: Active Tenders | D4: New Today | G4: Corrigenda | J4: Closing in 7 Days
A5: =COUNTIF('Master Tenders'!Q:Q,"Open")+COUNTIF('Master Tenders'!Q:Q,"Extended") | D5: =COUNTIFS('Master Tenders'!R:R,TODAY(),'Master Tenders'!Q:Q,"New") | G5: =COUNTIF('Master Tenders'!Q:Q,"Corrigendum") | J5: =COUNTIFS('Master Tenders'!N:N,">="&TODAY(),'Master Tenders'!N:N,"<="&TODAY()+7)
A9: Update Control | J9: Technology Summary
A10: Last Update | J10: Technology | K10: Count
A11: Update Mode | B11: Manual / External Script | J11: Solar | K11: =COUNTIF('Master Tenders'!F:F,"Solar")
A12: Workbook Status | B12: Ready | J12: Solar + BESS | K12: =COUNTIF('Master Tenders'!F:F,"Solar + BESS")
A13: Instructions | B13: Use the VBA module in the package to create an Update Tenders button. | J13: FDRE | K13: =COUNTIF('Master Tenders'!F:F,"FDRE")
J14: Wind | K14: =COUNTIF('Master Tenders'!F:F,"Wind")
A15: Operational Checks
A16: Metric | B16: Value | D16: Status Summary | J16: BESS | K16: =COUNTIF('Master Tenders'!F:F,"BESS")
A17: Duplicate Records | B17: =COUNTIF('Master Tenders'!Z:Z,"Duplicate") | D17: Status | E17: Count
A18: Urgent Deadlines | B18: =COUNTIF('Master Tenders'!X:X,"Urgent") | D18: New | E18: =COUNTIF('Master Tenders'!Q:Q,"New")
A19: Expired but Open | B19: =COUNTIFS('Master Tenders'!X:X,"Expired",'Master Tenders'!Q:Q,"Open") | D19: Open | E19: =COUNTIF('Master Tenders'!Q:Q,"Open")
A20: Enabled Agencies | B20: =COUNTIF('Agency Master'!D:D,"Yes") | D20: Extended | E20: =COUNTIF('Master Tenders'!Q:Q,"Extended")
D21: Corrigendum | E21: =COUNTIF('Master Tenders'!Q:Q,"Corrigendum")
D22: Closed | E22: =COUNTIF('Master Tenders'!Q:Q,"Closed")
D23: Awarded | E23: =COUNTIF('Master Tenders'!Q:Q,"Awarded")
A25: Connector Readiness
A26: Metric | B26: Value | D26: Metric | E26: Value | G26: Metric | H26: Value | J26: Metric | K26: Value
A27: Dedicated Connectors | B27: =COUNTIF('Source Registry'!E:E,"Yes") | D27: Documents Pending | E27: =COUNTIF('Document Queue'!H:H,"Pending") | G27: Pending Import Batches | H27: =COUNTIF('Import Control'!L:L,"Pending") | J27: Execution Runs | K27: =COUNTA('Execution Control'!A:A)-1
A28: Generic / Planned | B28: =COUNTIF('Source Registry'!E:E,"No") | D28: Documents Extracted | E28: =COUNTIF('Document Queue'!I:I,"Extracted") | G28: Imported Batches | H28: =COUNTIF('Import Control'!L:L,"Imported") | J28: Backups Created | K28: =COUNTIF('Execution Control'!L:L,"<>")-1
A29: Last Connector Tests | B29: =COUNT('Source Registry'!G:G) | D29: PDF Results Pending Review | E29: =COUNTIF('PDF Extraction Results'!S:S,"Pending Review") | G29: Validation Errors | H29: =COUNTIF('Validation Errors'!J:J,"Pending") | J29: Daily Summaries | K29: =COUNTA('Daily Summary'!A:A)-1
A30: Live Sample Records | B30: =COUNTIF('Master Tenders'!V:V,"*Live-source sample*")+COUNTIF('Master Tenders'!V:V,"*official NTPC*") | D30: Changes Pending Decision | E30: =COUNTIF('Change Review'!L:L,"Pending") | G30: Successful Write-Backs | H30: =COUNTIF('Writeback Audit'!K:K,"Success") | J30: V6 Connectors | K30: =COUNTIF('Agency Coverage'!D:D,"V6")
D31: Approved Changes | E31: =COUNTIF('Change Review'!L:L,"Approve") | G31: Failed Write-Backs | H31: =COUNTIF('Writeback Audit'!K:K,"Failed") | J31: Total Capacity MW | K31: =SUM('Master Tenders'!G:G)
G32: State Connectors Added | H32: =COUNTIFS('Agency Coverage'!D:D,"V5",'Agency Coverage'!A:A,"<>Central") | J32: Storage Capacity MW | K32: =SUMIFS('Master Tenders'!G:G,'Master Tenders'!H:H,"Yes")
A34: V7 Live Snapshot
A35: Metric | B35: Value | D35: Metric | E35: Value | G35: Metric | H35: Value | J35: Metric | K35: Value
A36: Verified tender records | B36: =COUNTA('Master Tenders'!A2:A19) | D36: Total verified records | E36: =COUNTA('Master Tenders'!A2:A27) | G36: Eligible records | H36: 16 | J36: Active eligible tenders | K36: 8
A37: Agencies populated | B37: =COUNTA(UNIQUE(FILTER('Master Tenders'!C2:C19,'Master Tenders'!C2:C19<>""))) | D37: Agencies populated | E37: =COUNTA(UNIQUE(FILTER('Master Tenders'!C2:C27,'Master Tenders'!C2:C27<>""))) | G37: Excluded records | H37: 10 | J37: Closed/expired removed | K37: 8
A38: Open / Extended | B38: =COUNTIF('Master Tenders'!Q2:Q19,"Open")+COUNTIF('Master Tenders'!Q2:Q19,"Extended") | D38: Current opportunities | E38: =COUNTIF('Master Tenders'!AF2:AF27,"Current Opportunity") | G38: Minimum capacity MW | H38: 100 | J38: Notification date column | K38: Added
A39: Storage-linked MW | B39: =SUMIFS('Master Tenders'!G2:G19,'Master Tenders'!H2:H19,"Yes") | D39: Needs status check | E39: =COUNTIF('Master Tenders'!AF2:AF27,"Needs Status Check") | G39: Rooftop excluded | H39: Yes | J39: Corrigendum dates in Master | K39: Added
A40: Manual verification agencies | B40: =COUNTA('Manual Verification Queue'!C5:C14) | D40: High evidence records | E40: =COUNTIF('Master Tenders'!AE2:AE27,">=5") | G40: KUSUM excluded | H40: Yes | J40: Separate corrigendum sheet | K40: Removed
A41: Snapshot date | B41: 46236 | D41: NHPC records added | E41: =COUNTIF('Master Tenders'!C2:C27,"NHPC") | G41: Unknown capacity excluded | H41: Yes | J41: Separate closed sheet | K41: Removed
D42: MP / Rajasthan records | E42: =COUNTIF('Master Tenders'!B2:B27,"Madhya Pradesh")+COUNTIF('Master Tenders'!B2:B27,"Rajasthan") | G42: Eligible current opportunities | H42: =COUNTIF('Master Tenders'!AF2:AF17,"Current Opportunity") | J42: Snapshot date | K42: 46236
A44: V11 Procurement-Clause Review
A45: Metric | B45: Value | D45: Metric | E45: Value | G45: Metric | H45: Value | J45: Metric | K45: Value
A46: Eligible procurement tenders | B46: 4 | D46: Version | E46: 12.0 | G46: Dedicated connectors | H46: 31 | J46: Repository package | K46: GitHub-ready
A47: Supply/install/O&M removed | B47: 2 | D47: Daily schedule | E47: 08:00 IST | G47: Connector health sheet | H47: Added | J47: Workflow | K47: Validated structure
A48: Expired legacy records removed | B48: 2 | D48: Workflow enabled | E48: After repository setup | G48: PLF rule library | H48: Added | J48: PLF parser tests | K48: Expanded
A49: Detailed RfS verified | B49: 2 | D49: Automatic workbook commit | E49: Yes | G49: Clause QA workflow | H49: Added | J49: Evidence snippets | K49: Page-aware
A50: BESS document review pending | B50: 2 | D50: Automatic closed removal | E50: Yes | G50: Retries / backoff | H50: Enabled | J50: Connector health JSON | K50: Guaranteed output
A51: External energy rules captured | B51: 2 | D51: Same-row corrigenda | E51: Yes | G51: HTML + PDF extraction | H51: Enabled | J51: Dry-run safety | K51: Push defaults to dry-run
A52: Penalty rules captured | B52: 2 | D52: Restricted portal handling | E52: Manual queue | G52: Confidence scoring | H52: Enabled | J52: Live schedule | K52: 08:00 IST
G53: Production claim | H53: Requires live source testing | J53: Production approval | K53: After connector live tests

Sheet Master Tenders
A1: Tender ID | B1: Category | C1: Agency | D1: State | E1: Tender Number | F1: Technology | G1: Capacity MW | H1: Storage Required | I1: Storage Hours | J1: Dispatch Condition | K1: Minimum PLF % | L1: EMD | M1: BG / PBG Conditions | N1: Bid Submission Date | O1: Technical Opening | P1: Financial Opening | Q1: Status | R1: Last Updated | S1: Corrigendum Count | T1: Tender URL | U1: Document URL | V1: Remarks | W1: Days to Deadline | X1: Deadline Alert | Y1: Duplicate Key | Z1: Duplicate Flag | AA1: Change Fingerprint | AB1: Verified On | AC1: Source Quality | AD1: Data Completeness | AE1: Evidence Score | AF1: Opportunity Class | AG1: Tender Notification Date | AH1: Corrigendum Date(s) | AI1: Latest Corrigendum Date | AJ1: Corrigendum Details | AK1: Procurement Model | AL1: Supply Window / Dispatch Selection | AM1: Daily Supply Obligation | AN1: Monthly Minimum / Reconciliation | AO1: Annual PLF / CUF / Energy Requirement | AP1: Allowed Shortfall / Availability Tolerance | AQ1: Under-Supply Penalty | AR1: External / Exchange Energy Allowed | AS1: Maximum External Energy | AT1: Charging / External Energy Conditions | AU1: Third-Party / Merchant Use | AV1: Detailed Source Document | AW1: Technical Review Status | AX1: First Seen By Automation | AY1: Last Seen By Automation | AZ1: Source Record Hash
A2: MSEDCL-BESS-2000 | B2: Maharashtra | C2: MSEDCL | D2: Maharashtra | E2: RfS-2000MW-4000MWh-BESS-2026 | F2: BESS | G2: 2000 | H2: Yes | I2: 2 | J2: Tariff-based competitive bidding | M2: As per RfS | Q2: Corrigendum | R2: 46236 | S2: 2 | T2: https://www.mahadiscom.in/en/supplier/tenders/ | V2: Corrigendum-2 published 22-Jul-2026; deadline not visible on listing | W2: =IF(N2="","",N2-TODAY()) | X2: =IF(W2="","",IF(W2<0,"Expired",IF(W2<=3,"Urgent",IF(W2<=7,"Due in 7 Days","Normal")))) | Y2: =UPPER(TRIM(C2&"|"&E2)) | Z2: =IF(Y2="","",IF(COUNTIF($Y$2:$Y$501,Y2)>1,"Duplicate","Unique")) | AA2: =IF(A5="","",C5&"|"&E5&"|"&TEXT(N5,"yyyymmdd")&"|"&Q5&"|"&S5&"|"&TEXT(AI5,"yyyymmdd")) | AB2: 46236 | AC2: Official agency page | AD2: Partial | AE2: =IF(A5="","",IF(AC5="Official agency page",3,IF(AC5="Official government portal",3,IF(AC5="Official tender document",4,1)))+IF(AD5="Core fields",2,1)) | AF2: =IF(A5="","",IF(OR(Q5="Open",Q5="Extended"),"Current Opportunity",IF(Q5="Corrigendum","Needs Status Check",IF(Q5="Evaluation","Under Evaluation","Historical / Closed")))) | AG2: 46203 | AH2: 2026-07-07; 2026-07-22 | AI2: 46225 | AJ2: Addendum-1 and Addendum-2 published 07-Jul-2026; Corrigendum-2 published 22-Jul-2026 | AK2: Standalone BESS under tariff-based competitive bidding | AL2: Dispatch/charging schedule governed by RfS and BESPA | AM2: PLF is not applicable to standalone BESS; daily cycle and availability obligations require current 2026 RfS review | AN2: Monthly availability/payment condition not verified from accessible current document text | AO2: Annual PLF/CUF not applicable; annual availability requirement not verified | AP2: Not verified from accessible current 2026 document text | AQ2: Not verified from accessible current 2026 document text | AR2: Charging source and grid/exchange charging permission not verified | AS2: Not verified | AT2: Current 2026 tender and corrigenda are visible on MSEDCL, but detailed clauses require opening the RfS/corrigendum PDF | AU2: Merchant-use rights not verified | AV2: https://www.mahadiscom.in/en/supplier/tenders/ | AW2: Tender confirmed; commercial clause extraction pending | AY2: 46315.34
A3: SECI000240 | B3: Central | C3: SECI | E3: SECI/C&P/IPP/13/0020/25-26 | F3: FDRE | G3: 1000 | H3: No | Q3: Open | R3: 46237.26 | S3: 0 | T3: https://www.seci.co.in/tender-details/YmZ3 | V3: | SECI000240 | SECI-2026-TN000004 | SECI/C&P/IPP/13/0020/25-26 | RfS for Supply of 1000 MW Firm and Dispatchable Renewable Energy Round-the-Clock (FDRE-RTC) Power from ISTS-Connected RE Power Projects in India (SECI-FDRE-RTC-V) | 10/03/2026 | 20/07/2026 | View Details | SECI000240 | SECI-2026-TN000004 | SECI/C&P/IPP/13/0020/25-26 | RfS for Supply of 1000 MW Firm and Dispatchable Renewable Energy Round-the-Clock (FDRE-RTC) Power from ISTS-Connected RE Power Projects in India (SECI-FDRE-RTC-V) | 10/03/2026 | 20/07/2026 | View Details | W3: =IF(N3="","",N3-TODAY()) | X3: =IF(W3="","",IF(W3<0,"Expired",IF(W3<=3,"Urgent",IF(W3<=7,"Due in 7 Days","Normal")))) | Y3: =UPPER(TRIM(C3&"|"&E3)) | Z3: =IF(Y3="","",IF(COUNTIF($Y$2:$Y$501,Y3)>1,"Duplicate","Unique")) | AC3: Official agency page | AX3: 46237.26 | AY3: 46315.34 | AZ3: 014f0276d0bedb946c97bc1d31fd766e19a14673016f74b3288a3d56aab0e824
A4: SECI000258 | B4: Central | C4: SECI | E4: SECI/C&P/IPP/13/0006/26-27 | F4: FDRE | G4: 1500 | H4: Yes | I4: 4 | Q4: Open | R4: 46243.177 | S4: 0 | T4: https://www.seci.co.in/tender-details/Ymd_ | V4: | SECI000258 | SECI-2026-TN000014 | SECI/C&P/IPP/13/0006/26-27 | RfS for assured Peak Supply of 6000 MWh (1500 MW x 4 Hrs.) from ISTS-Connected RE Projects (SECI-FDRE-IX) | 05/06/2026 | 07/08/2026 | View Details | SECI000258 | SECI-2026-TN000014 | SECI/C&P/IPP/13/0006/26-27 | RfS for assured Peak Supply of 6000 MWh (1500 MW x 4 Hrs.) from ISTS-Connected RE Projects (SECI-FDRE-IX) | 05/06/2026 | 07/08/2026 | View Details | W4: =IF(N4="","",N4-TODAY()) | X4: =IF(W4="","",IF(W4<0,"Expired",IF(W4<=3,"Urgent",IF(W4<=7,"Due in 7 Days","Normal")))) | Y4: =UPPER(TRIM(C4&"|"&E4)) | Z4: =IF(Y4="","",IF(COUNTIF($Y$2:$Y$501,Y4)>1,"Duplicate","Unique")) | AC4: Official agency page | AX4: 46243.177 | AY4: 46315.34 | AZ4: 63f0892f32e39002cd45d1e3a78c55637433070adc204427287bd864299eff80
A5: SECI000278 | B5: Central | C5: SECI | E5: SECI/C&P/IPP/15/0009/26-27 | F5: Solar | G5: 700 | H5: No | Q5: Open | R5: 46269.318 | S5: 0 | T5: https://www.seci.co.in/tender-details/YmV_ | V5: | SECI000278 | SECI-2026-TN000027 | SECI/C&P/IPP/15/0009/26-27 | 700 MW ISTS-Connected Solar PV Power Projects in India under TBCB (C&I-1) | 03/09/2026 | 30/10/2026 | View Details | SECI000278 | SECI-2026-TN000027 | SECI/C&P/IPP/15/0009/26-27 | 700 MW ISTS-Connected Solar PV Power Projects in India under TBCB (C&I-1) | 03/09/2026 | 30/10/2026 | View Details | W5: =IF(N5="","",N5-TODAY()) | X5: =IF(W5="","",IF(W5<0,"Expired",IF(W5<=3,"Urgent",IF(W5<=7,"Due in 7 Days","Normal")))) | Y5: =UPPER(TRIM(C5&"|"&E5)) | Z5: =IF(Y5="","",IF(COUNTIF($Y$2:$Y$501,Y5)>1,"Duplicate","Unique")) | AC5: Official agency page | AX5: 46269.318 | AY5: 46315.34 | AZ5: 7824665aa0c60055256886b7aaf5ac91b1463e7827e8addcf186fc53ed5c458b
A6: SECI000286 | B6: Central | C6: SECI | E6: SECI/C&P/IPP/15/0010/26-27 | F6: BESS | G6: 800 | H6: Yes | I6: 4 | Q6: Open | R6: 46297.381 | S6: 0 | T6: https://www.seci.co.in/tender-details/Ympx | V6: | SECI000286 | SECI-2026-TN000032 | SECI/C&P/IPP/15/0010/26-27 | RfS for Supply of Energy from 800 MW/ 3200 MWh Standalone Battery Energy Storage Systems in India (SECI-ESS-IV) | 01/10/2026 | 30/10/2026 | View Details | SECI000286 | SECI-2026-TN000032 | SECI/C&P/IPP/15/0010/26-27 | RfS for Supply of Energy from 800 MW/ 3200 MWh Standalone Battery Energy Storage Systems in India (SECI-ESS-IV) | 01/10/2026 | 30/10/2026 | View Details | W6: =IF(N6="","",N6-TODAY()) | X6: =IF(W6="","",IF(W6<0,"Expired",IF(W6<=3,"Urgent",IF(W6<=7,"Due in 7 Days","Normal")))) | Y6: =UPPER(TRIM(C6&"|"&E6)) | Z6: =IF(Y6="","",IF(COUNTIF($Y$2:$Y$501,Y6)>1,"Duplicate","Unique")) | AC6: Official agency page | AX6: 46297.381 | AY6: 46315.34 | AZ6: 8038b9c673b234232243712421a064fdc5564f83be927e06286a43463e83fb1b
A7: SECI000289 | B7: Central | C7: SECI | E7: SECI/C&P/IPP/13/0012/26-27 | F7: FDRE | G7: 1200 | H7: Yes | I7: 4 | Q7: Open | R7: 46303.401 | S7: 0 | T7: https://www.seci.co.in/tender-details/Ymp- | V7: | SECI000289 | SECI-2026-TN000035 | SECI/C&P/IPP/13/0012/26-27 | RfS for Assured Peak Supply of 4800 MWh (1200 MW x 4 Hrs.) from ISTS-Connected RE Projects in India (SECI-FDRE-X) | 07/10/2026 | 29/10/2026 | View Details | SECI000289 | SECI-2026-TN000035 | SECI/C&P/IPP/13/0012/26-27 | RfS for Assured Peak Supply of 4800 MWh (1200 MW x 4 Hrs.) from ISTS-Connected RE Projects in India (SECI-FDRE-X) | 07/10/2026 | 29/10/2026 | View Details | W7: =IF(N7="","",N7-TODAY()) | X7: =IF(W7="","",IF(W7<0,"Expired",IF(W7<=3,"Urgent",IF(W7<=7,"Due in 7 Days","Normal")))) | Y7: =UPPER(TRIM(C7&"|"&E7)) | Z7: =IF(Y7="","",IF(COUNTIF($Y$2:$Y$501,Y7)>1,"Duplicate","Unique")) | AC7: Official agency page | AX7: 46303.401 | AY7: 46315.34 | AZ7: ddea91e8920c6f05a00cb8c5c42f00b52d1ec41a1a9f1c7b1fe735c184d95d52
A8: SECI000288 | B8: Central | C8: SECI | E8: SECI/C&P/IPP/12/0011/26-27 | F8: Wind | G8: 1200 | H8: No | Q8: Open | R8: 46303.401 | S8: 0 | T8: https://www.seci.co.in/tender-details/Ymp_ | V8: | SECI000288 | SECI-2026-TN000034 | SECI/C&P/IPP/12/0011/26-27 | RfS for 1200 MW ISTS-Connected Wind Power Projects in India (SECI-Tranche-XXI) | 07/10/2026 | 29/10/2026 | View Details | SECI000288 | SECI-2026-TN000034 | SECI/C&P/IPP/12/0011/26-27 | RfS for 1200 MW ISTS-Connected Wind Power Projects in India (SECI-Tranche-XXI) | 07/10/2026 | 29/10/2026 | View Details | W8: =IF(N8="","",N8-TODAY()) | X8: =IF(W8="","",IF(W8<0,"Expired",IF(W8<=3,"Urgent",IF(W8<=7,"Due in 7 Days","Normal")))) | Y8: =UPPER(TRIM(C8&"|"&E8)) | Z8: =IF(Y8="","",IF(COUNTIF($Y$2:$Y$501,Y8)>1,"Duplicate","Unique")) | AC8: Official agency page | AX8: 46303.401 | AY8: 46315.34 | AZ8: f78fab2d611bb0aa5e5cdc279685f3e2481353c8068bd750e95f5eb4b8948c8f
B9: Central | C9: NTPC REL | E9: 3 | F9: Solar | G9: 2100 | H9: No | Q9: Open | R9: 46315.34 | T9: https://ntpctender.ntpc.co.in/NITDetails/NITs/30370 | V9: SUPPLY OF SOLAR PV MODULES FOR 2100MW SOLAR PV PROJECT OF NTPC REL AT FATEHGARH AND BIKANER, RAJASTHAN (opens in a new tab) Renewable Energy 3 | NRE-CS-5800-004(MOD-01)-9 | SUPPLY OF SOLAR PV MODULES FOR 2100MW SOLAR PV PROJECT OF NTPC REL AT FATEHGARH AND BIKANER, RAJASTHAN (opens in a new tab) Renewable Energy | Renewable Energy | 24 Oct 2026 5:00 PM | View tender NRE-CS-5800-004(MOD-01)-9 (opens in a new tab) | W9: =IF(N9="","",N9-TODAY()) | X9: =IF(W9="","",IF(W9<0,"Expired",IF(W9<=3,"Urgent",IF(W9<=7,"Due in 7 Days","Normal")))) | Y9: =UPPER(TRIM(C9&"|"&E9)) | Z9: =IF(Y9="","",IF(COUNTIF($Y$2:$Y$501,Y9)>1,"Duplicate","Unique")) | AC9: Official agency page | AX9: 46315.34 | AY9: 46315.34 | AZ9: 372580ad68a1cb8f4796f1cc1acb5446dafd8bd8354920b25faf1fff320cf32b
B10: Central | C10: SJVN | E10: Hiring of 02 Nos. AC Commercial vehicle, 7-Seater SUV (Mahindra Bolero Neo N4) Taxi Vehicle (without Fuel) registered as tourist/cab vehicle in Rajast | F10: Solar | G10: 1000 | H10: No | Q10: Open | R10: 46315.34 | T10: https://sjvn.nic.in/en/tender | V10: Hiring of 02 Nos. AC Commercial vehicle, 7-Seater SUV (Mahindra Bolero Neo N4) Taxi Vehicle (without Fuel) registered as tourist/cab vehicle in Rajasthan along with driver for a period of 02 years” at 1000MW Bikaner Solar Power Project office, Rajasthan Hiring of 02 Nos. AC Commercial vehicle, 7-Seater SUV (Mahindra Bolero Neo N4) Taxi Vehicle (without Fuel) registered as tourist/cab vehicle in Rajasthan along with driver for a period of 02 years” at 1000MW Bikaner Solar Power Project office, Rajasthan | W10: =IF(N10="","",N10-TODAY()) | X10: =IF(W10="","",IF(W10<0,"Expired",IF(W10<=3,"Urgent",IF(W10<=7,"Due in 7 Days","Normal")))) | Y10: =UPPER(TRIM(C10&"|"&E10)) | Z10: =IF(Y10="","",IF(COUNTIF($Y$2:$Y$501,Y10)>1,"Duplicate","Unique")) | AC10: Official agency page | AX10: 46315.34 | AY10: 46315.34 | AZ10: ae9d8cf76c372228c5660ac5d38dc1c0b7e833c3a78a02407e10c8dbc57cff20
B11: Odisha | C11: GRIDCO | E11: Issuing Authority : CPM,RENA,GRIDCO Ltd Start Date of Selling Tender Paper : 10/16/2026 Date of Opening : 11/17/2026 05:00 PM Scope of Work : RFP for | F11: Solar + BESS | G11: 225 | H11: No | Q11: Open | R11: 46315.34 | T11: https://www.gridco.co.in/tender.aspx | V11: Issuing Authority : | CPM,RENA,GRIDCO Ltd | Start Date of Selling Tender Paper : | 10/16/2026 | Date of Opening : | 11/17/2026 05:00 PM | Scope of Work : | RFP for Consultancy Services for Environmental and Social Impact Assessment for the 225 MW Upper Indravati Floating Solar and Battery Energy Storage System Project, including evacuation infrastructure and associated transmission lines, Odisha | Tender Description : | RFP for Consultancy Services for Environmental and Social Impact Assessment for the 225 MW Upper Indravati Floating Solar and Battery Energy Storage System Project, including evacuation infrastructure and associated transmission lines, Odisha Issuing Authority : CPM,RENA,GRIDCO Ltd Start Date of Selling Tender Paper : 10/16/2026 Date of Opening : 11/17/2026 05:00 PM Scope of Work : RFP for Consultancy Services for Environmental and Social Impact Assessment for the 225 MW Upper Indravati Floating Solar and Battery Energy Storage System Project, including evacuation infra | W11: =IF(N11="","",N11-TODAY()) | X11: =IF(W11="","",IF(W11<0,"Expired",IF(W11<=3,"Urgent",IF(W11<=7,"Due in 7 Days","Normal")))) | Y11: =UPPER(TRIM(C11&"|"&E11)) | Z11: =IF(Y11="","",IF(COUNTIF($Y$2:$Y$501,Y11)>1,"Duplicate","Unique")) | AC11: Official agency page | AX11: 46315.34 | AY11: 46315.34 | AZ11: e6a1defdcdb58beebeabb1a028e0cf4d4d8f817b1c156825b172ad268d82b23c
B12: Odisha | C12: GRIDCO | E12: Scope of Work : | F12: Solar + BESS | G12: 225 | H12: No | Q12: Open | R12: 46315.34 | T12: https://www.gridco.co.in/tender.aspx | V12: RFP for Consultancy Services for Environmental and Social Impact Assessment for the 225 MW Upper Indravati Floating Solar and Battery Energy Storage System Project, including evacuation infrastructure and associated transmission lines, Odisha Scope of Work : RFP for Consultancy Services for Environmental and Social Impact Assessment for the 225 MW Upper Indravati Floating Solar and Battery Energy Storage System Project, including evacuation infrastructure and associated transmission lines, Odisha | W12: =IF(N12="","",N12-TODAY()) | X12: =IF(W12="","",IF(W12<0,"Expired",IF(W12<=3,"Urgent",IF(W12<=7,"Due in 7 Days","Normal")))) | Y12: =UPPER(TRIM(C12&"|"&E12)) | Z12: =IF(Y12="","",IF(COUNTIF($Y$2:$Y$501,Y12)>1,"Duplicate","Unique")) | AC12: Official agency page | AX12: 46315.34 | AY12: 46315.34 | AZ12: 52e32cf0cd1ed71e5baab7ff0d2500d2184a637ef83b953a80ca61e2fc9f80ae
B13: Odisha | C13: GRIDCO | E13: Tender Description : | F13: Solar + BESS | G13: 225 | H13: No | Q13: Open | R13: 46315.34 | T13: https://www.gridco.co.in/tender.aspx | V13: RFP for Consultancy Services for Environmental and Social Impact Assessment for the 225 MW Upper Indravati Floating Solar and Battery Energy Storage System Project, including evacuation infrastructure and associated transmission lines, Odisha Tender Description : RFP for Consultancy Services for Environmental and Social Impact Assessment for the 225 MW Upper Indravati Floating Solar and Battery Energy Storage System Project, including evacuation infrastructure and associated transmission lines, Odisha | W13: =IF(N13="","",N13-TODAY()) | X13: =IF(W13="","",IF(W13<0,"Expired",IF(W13<=3,"Urgent",IF(W13<=7,"Due in 7 Days","Normal")))) | Y13: =UPPER(TRIM(C13&"|"&E13)) | Z13: =IF(Y13="","",IF(COUNTIF($Y$2:$Y$501,Y13)>1,"Duplicate","Unique")) | AC13: Official agency page | AX13: 46315.34 | AY13: 46315.34 | AZ13: 791b5092eab5e02201c5ba3340df5b560b094983458e49be81970948be5467bf

Sheet Agency Master
A1: Category | B1: Agency | C1: State / Region | D1: Enabled | E1: Primary Tender Page | F1: Secondary / eProcurement Page | G1: Scan Method | H1: Notes
A2: Central | B2: SECI | C2: All India | D2: Yes | E2: https://www.seci.co.in/ | G2: HTML/PDF
A3: Central | B3: NTPC REL | C3: All India | D3: Yes | E3: https://www.ntpc.co.in/ | G3: HTML/PDF
A4: Central | B4: NHPC | C4: All India | D4: Yes | E4: https://www.nhpcindia.com/ | G4: HTML/PDF
A5: Central | B5: SJVN | C5: All India | D5: Yes | E5: https://sjvn.nic.in/ | G5: HTML/PDF
A6: Central | B6: NLCIL | C6: All India | D6: Yes | E6: https://www.nlcindia.in/ | G6: HTML/PDF
A7: Central | B7: GUVNL (ISTS) | C7: All India | D7: Yes | E7: https://www.guvnl.com/ | G7: HTML/PDF
A8: Central | B8: REMCL | C8: All India | D8: Yes | E8: https://www.remcl.in/ | G8: HTML/PDF
A9: Rajasthan | B9: RUVNL | C9: Rajasthan | D9: Yes | G9: HTML/PDF | H9: Verify current official tender page
A10: Rajasthan | B10: RVPN | C10: Rajasthan | D10: Yes | E10: https://energy.rajasthan.gov.in/rvpnl | G10: HTML/PDF
A11: Karnataka | B11: KREDL | C11: Karnataka | D11: Yes | E11: https://kredl.karnataka.gov.in/ | G11: HTML/PDF
A12: Karnataka | B12: KPTCL | C12: Karnataka | D12: Yes | E12: https://kptcl.karnataka.gov.in/ | G12: HTML/PDF
A13: Karnataka | B13: KPCL | C13: Karnataka | D13: Yes | E13: https://karnatakapower.com/ | G13: HTML/PDF
A14: Madhya Pradesh | B14: MPUVNL | C14: Madhya Pradesh | D14: Yes | E14: https://www.mprenewable.nic.in/ | G14: HTML/PDF
A15: Madhya Pradesh | B15: MPPMCL | C15: Madhya Pradesh | D15: Yes | E15: https://mppmcl.com/ | G15: HTML/PDF
A16: Madhya Pradesh | B16: MP Urja Vikas Nigam | C16: Madhya Pradesh | D16: Yes | E16: https://www.mprenewable.nic.in/ | G16: HTML/PDF
A17: Maharashtra | B17: MSEDCL | C17: Maharashtra | D17: Yes | E17: https://www.mahadiscom.in/ | G17: HTML/PDF
A18: Maharashtra | B18: MAHAGENCO | C18: Maharashtra | D18: Yes | E18: https://www.mahagenco.in/ | G18: HTML/PDF
A19: Gujarat | B19: GUVNL | C19: Gujarat | D19: Yes | E19: https://www.guvnl.com/ | G19: HTML/PDF
A20: Gujarat | B20: GPCL | C20: Gujarat | D20: Yes | E20: https://gpcl.gujarat.gov.in/ | G20: HTML/PDF
A21: Andhra Pradesh | B21: APSPDCL | C21: Andhra Pradesh | D21: Yes | E21: https://www.apspdcl.in/ | G21: HTML/PDF
... A23: Andhra Pradesh | B23: NREDCAP | C23: Andhra Pradesh | D23: Yes | E23: https://nredcap.in/ | G23: HTML/PDF
A24: Telangana | B24: TGNPDCL | C24: Telangana | D24: Yes | G24: HTML/PDF | H24: Verify current official tender page
A25: Telangana | B25: TSSPDCL | C25: Telangana | D25: Yes | E25: https://www.tssouthernpower.com/ | G25: HTML/PDF
A26: Tamil Nadu | B26: TNGECL | C26: Tamil Nadu | D26: Yes | G26: HTML/PDF | H26: Verify current official tender page
A27: Tamil Nadu | B27: TANTRANSCO | C27: Tamil Nadu | D27: Yes | E27: https://www.tantransco.gov.in/ | G27: HTML/PDF
A28: Odisha | B28: GRIDCO | C28: Odisha | D28: Yes | E28: https://www.gridco.co.in/ | G28: HTML/PDF
A29: Haryana | B29: HAREDA | C29: Haryana | D29: Yes | E29: https://hareda.gov.in/ | G29: HTML/PDF
A30: Punjab | B30: PSPCL | C30: Punjab | D30: Yes | E30: https://www.pspcl.in/ | G30: HTML/PDF
A31: Uttar Pradesh | B31: UPNEDA | C31: Uttar Pradesh | D31: Yes | E31: https://upneda.org.in/ | G31: HTML/PDF
A32: Bihar | B32: BSPHCL | C32: Bihar | D32: Yes | E32: https://www.bsphcl.co.in/ | G32: HTML/PDF
A33: Others | B33: Central Public Procurement Portal | C33: All India | D33: Yes | E33: https://eprocure.gov.in/eprocure/app | G33: Portal
A34: Others | B34: Government e-Marketplace | C34: All India | D34: No | E34: https://gem.gov.in/ | G34: Portal | H34: Enable where relevant

Sheet Update Log
A1: Timestamp | B1: Agency | C1: Tender ID | D1: Action | E1: Previous Value | F1: New Value | G1: Result | H1: Error / Notes

Sheet New Tenders
A1: New Tenders
A4: Tender ID | B4: Category | C4: Agency | D4: State | E4: Tender Number | F4: Technology | G4: Capacity MW | H4: Storage Required | I4: Storage Hours | J4: Dispatch Condition | K4: Minimum PLF % | L4: EMD | M4: BG / PBG Conditions | N4: Bid Submission Date | O4: Technical Opening | P4: Financial Opening | Q4: Status | R4: Last Updated | S4: Corrigendum Count | T4: Tender URL | U4: Document URL | V4: Remarks
A5: =FILTER('Master Tenders'!A2:V501,'Master Tenders'!Q2:Q501="New","No new tenders")

Sheet Settings
A1: Tracker Settings & Classification Rules
A4: Setting | B4: Value | D4: Keyword | E4: Mapped Technology | F4: Priority | H4: Execution Setting | I4: Value | J4: Notes
A5: Default lookback days | B5: 30 | D5: solar + bess | E5: Solar + BESS | F5: 1 | H5: Direct XLSX write-back | I5: Yes | J5: Uses Python openpyxl in package
A6: Request timeout seconds | B6: 45 | D6: battery energy storage | E6: BESS | F6: 1 | H6: Create timestamped backup | I6: Yes | J6: Before any live write
A7: Download PDFs | B7: Yes | D7: firm and dispatchable renewable energy | E7: FDRE | F7: 1 | H7: Default dry-run | I7: Yes | J7: Recommended until tested
A8: Update existing tenders | B8: Yes | D8: fdre | E8: FDRE | F8: 1 | H8: Update formulas after write | I8: Yes | J8: Excel recalculates on open
A9: Close expired tenders automatically | B9: No | D9: wind solar hybrid | E9: Hybrid | F9: 2 | H9: Daily summary enabled | I9: Yes | J9: Writes run-level totals
A10: Output workbook name | B10: Renewable_Tender_Tracker.xlsx | D10: hybrid renewable | E10: Hybrid | F10: 2 | H10: Export management report | I10: Yes | J10: Workbook sheet
D11: wind | E11: Wind | F11: 3 | H11: Scheduled cloud execution | I11: Optional | J11: Templates included
A12: Automation Parameter | B12: Value | D12: solar | E12: Solar | F12: 4 | H12: Email notifications | I12: Not configured | J12: Requires mail provider
A13: Auto-close expired records | B13: No | D13: pumped storage | E13: Pumped Storage | F13: 1 | H13: Maximum input rows per run | I13: 2000
A14: Duplicate handling | B14: Skip and log | D14: round the clock | E14: RTC | F14: 2 | H14: Workbook password | I14: Not configured | J14: Do not store secrets in files
A15: History retention days | B15: 365 | H15: Log retention days | I15: 365
A16: Deadline alert window | B16: 7
A17: Urgent alert window | B17: 3
A18: Preferred output format | B18: xlsx / xlsm-ready
A20: Document Processing Setting | B20: Value | D20: Import / Writeback Setting | E20: Value | F20: Notes
A21: PDF download folder | B21: downloads | D21: Import batch size | E21: 500 | F21: Maximum rows per file
A22: Extracted text folder | B22: extracted_text | D22: Required duplicate fields | E22: Agency + Tender Number
A23: Maximum PDF size MB | B23: 50 | D23: Reject blank tender number | E23: Yes
A24: Minimum auto-approval confidence | B24: 0.9 | D24: Reject blank agency | E24: Yes
A25: OCR fallback enabled | B25: No | D25: Allow unknown technology | E25: Yes | F25: Mapped to Other
A26: Keep raw snapshots | B26: Yes | D26: Write audit for every change | E26: Yes
A27: Apply approved changes automatically | B27: No | D27: Archive processed files | E27: Yes
A28: Document hash algorithm | B28: SHA-256 | D28: Auto-create review items | E28: Yes | F28: For conflicting values
D29: Rollback file enabled | E29: Yes | F29: Creates pre-write snapshot

Sheet Tender Intake
A1: Tender Intake / Import Staging
A3: Paste newly collected tender data here. The updater framework validates, de-duplicates, and appends approved records to Master Tenders.
A5: Tender ID | B5: Category | C5: Agency | D5: State | E5: Tender Number | F5: Technology | G5: Capacity MW | H5: Storage Required | I5: Storage Hours | J5: Dispatch Condition | K5: Minimum PLF % | L5: EMD | M5: BG / PBG Conditions | N5: Bid Submission Date | O5: Technical Opening | P5: Financial Opening | Q5: Status | R5: Last Updated | S5: Corrigendum Count | T5: Tender URL | U5: Document URL | V5: Remarks

Sheet Tender History
A1: Tender Change History
A4: History ID | B4: Timestamp | C4: Tender ID | D4: Agency | E4: Tender Number | F4: Change Type | G4: Field Changed | H4: Old Value | I4: New Value | J4: Source URL | K4: Notes

Sheet Deadline Calendar
A1: Upcoming Bid Submission Deadlines
A4: Tender ID | B4: Agency | C4: Tender Number | D4: Technology | E4: Submission Date | F4: Days Left | G4: Status | H4: Tender URL
A5: {=_xlfn._xlws.FILTER(CHOOSE({1,2,3,4,5,6,7,8},'Master Tenders'!A2:A501,'Master Tenders'!C2:C501,'Master Tenders'!E2:E501,'Master Tenders'!F2:F501,'Master Tenders'!N2:N501,'Master Tenders'!W2:W501,'Master Tenders'!Q2:Q501,'Master Tenders'!T2:T501),('Master Tenders'!N2:N501>=TODAY())*('Master Tenders'!N2:N501<=TODAY()+30),"No deadlines in next 30 days")}
A6: SECI000258
A7: SJVN-BESS2
A8: SJVN-BESS2
A9: SJVN-GEM7789243
A10: SECI000249
A11: NTPC29985
A12: SJVN-BESS2
A13: SJVN-GEM7789243

Sheet Source Registry
A1: Agency Source Registry & Connector Readiness
A3: Official source URLs are configuration inputs. Connector status indicates whether V3 contains a dedicated parser or only a generic framework.
A5: Category | B5: Agency | C5: Official Source URL | D5: Source Type | E5: Dedicated Connector | F5: Connector Status | G5: Last Test Date | H5: Authentication | I5: Expected Fields | J5: Notes
A6: Central | B6: SECI | C6: https://seci.co.in/tenders/ | D6: HTML table/details | E6: Yes | F6: V3 parser included | G6: 46236 | H6: None | I6: ID, reference, title, publication date, submission date, detail link | J6: Official tender listing
A7: Central | B7: NTPC REL | C7: https://ntpctender.ntpc.co.in/Index/Search?Region=10&Type=Reg | D7: HTML search/details | E7: Yes | F7: V3 parser included | G7: 46236 | H7: None | I7: NIT no., title, closing/submission/opening dates, EMD, corrigendum | J7: Renewable Energy region search
A8: Central | B8: NHPC | C8: https://www.nhpcindia.com/ | D8: HTML/PDF | E8: Yes | F8: V4 parser included | G8: 46236 | H8: None | I8: Title, notice date, deadline, link | J8: Dedicated parser planned
A9: Central | B9: SJVN | C9: https://sjvn.nic.in/en/tender | D9: HTML details | E9: Yes | F9: V4 parser included | G9: 46236 | H9: None | I9: Tender ref., title, NIT date, submission date, detail link | J9: Dedicated parser planned
A10: Central | B10: NLCIL | C10: https://www.nlcindia.in/ | D10: HTML/PDF | E10: No | F10: Generic connector only | H10: None | I10: Title, date, deadline, link | J10: Dedicated parser planned
A11: Central | B11: REMCL | C11: https://www.remcl.in/ | D11: HTML/PDF | E11: No | F11: Generic connector only | H11: None | I11: Title, date, deadline, link | J11: Dedicated parser planned
A12: Central | B12: GUVNL (ISTS) | C12: https://www.guvnl.com/ | D12: HTML/PDF | E12: No | F12: Generic connector only | H12: None | I12: Title, date, deadline, link | J12: Dedicated parser planned
A13: Others | B13: Central Public Procurement Portal | C13: https://eprocure.gov.in/eprocure/app | D13: Portal | E13: No | F13: Manual/export integration | H13: Portal controls | I13: Tender no., title, dates, organisation, document links | J13: Portal restrictions may apply

Sheet Extraction Rules
A1: Rule-Based Tender Field Extraction
A4: Field | B4: Pattern / Keyword | C4: Output | D4: Priority | E4: Example Match | F4: Enabled | G4: Notes
A5: Technology | B5: solar + bess|solar.*battery | C5: Solar + BESS | D5: 1 | E5: 70 MW solar paired with 25 MW / 50 MWh BESS | F5: Yes
A6: Technology | B6: firm and dispatchable|fdre | C6: FDRE | D6: 1 | E6: Firm and Dispatchable Renewable Energy | F6: Yes
A7: Technology | B7: wind solar hybrid|hybrid renewable | C7: Hybrid | D7: 2 | E7: Wind-Solar Hybrid | F7: Yes
A8: Technology | B8: battery energy storage|\bbess\b | C8: BESS | D8: 2 | E8: 240 MW / 960 MWh BESS | F8: Yes
A9: Technology | B9: pumped storage|\bpsp\b | C9: Pumped Storage | D9: 1 | E9: 1500 MW / 12000 MWh Pumped Storage | F9: Yes
A10: Technology | B10: \bwind\b | C10: Wind | D10: 3 | E10: 45.6 MW Wind Power Project | F10: Yes
A11: Technology | B11: \bsolar\b|solar pv | C11: Solar | D11: 4 | E11: Grid Connected Solar PV | F11: Yes
A12: Storage Hours | B12: (\d+(?:\.\d+)?)\s*(?:hour|hr|hrs) | C12: Captured hours | D12: 1 | E12: 500 MW x 2 Hrs. | F12: Yes | G12: Direct text pattern
A13: Storage Hours | B13: (\d+(?:\.\d+)?)\s*mw\s*/\s*(\d+(?:\.\d+)?)\s*mwh | C13: MWh / MW | D13: 2 | E13: 240 MW / 960 MWh | F13: Yes | G13: Calculated duration
A14: Capacity MW | B14: (\d+(?:\.\d+)?)\s*mw | C14: Captured MW | D14: 1 | E14: 500 MW | F14: Yes | G14: Use context to avoid transformer ratings
A15: Energy MWh | B15: (\d+(?:\.\d+)?)\s*mwh | C15: Captured MWh | D15: 1 | E15: 6000 MWh | F15: Yes
A16: Status | B16: corrigendum|amendment | C16: Corrigendum | D16: 1 | E16: Corrigendum Available | F16: Yes
A17: Status | B17: extension|extended|revised.*date | C17: Extended | D17: 2 | E17: Revised Bid Open Date | F17: Yes
A18: Status | B18: cancelled|canceled | C18: Cancelled | D18: 1 | E18: Tender Cancelled | F18: Yes
A19: Dispatch | B19: peak supply|peak hours | C19: Peak | D19: 1 | E19: Assured Peak Supply | F19: Yes
A20: Dispatch | B20: round[- ]the[- ]clock|\brtc\b | C20: RTC | D20: 1 | E20: FDRE-RTC | F20: Yes
A21: Minimum PLF | B21: minimum.*plf.*?(\d+(?:\.\d+)?)% | C21: Captured % | D21: 1 | E21: minimum PLF 80% | F21: Yes | G21: Usually from RfS/PDF
A22: EMD | B22: emd(?: cost| amount)?\s*[:\-]?\s*(?:rs\.?|₹)?\s*([\d,]+(?:\.\d+)?) | C22: Captured amount | D22: 1 | E22: EMD Cost: 2000000 | F22: Yes

Sheet Connector Runs
A1: Connector Run Log
A4: Run ID | B4: Started | C4: Finished | D4: Agency | E4: Source URL | F4: Records Found | G4: New | H4: Updated | I4: Errors | J4: Result

Sheet Document Queue
A1: Tender Document Download & Extraction Queue
A3: Add tender/RfS/corrigendum PDF URLs here. The V4 Python engine downloads documents, extracts text, and produces review-ready field suggestions.
A5: Queue ID | B5: Tender ID | C5: Agency | D5: Tender Number | E5: Document Type | F5: Document URL | G5: Local File | H5: Download Status | I5: Extraction Status | J5: Pages | K5: Text Characters | L5: Document Hash | M5: Last Attempt | N5: Error / Notes

Sheet PDF Extraction Results
A1: PDF Tender Field Extraction Results
A4: Extraction ID | B4: Queue ID | C4: Tender ID | D4: Agency | E4: Document Type | F4: Technology | G4: Capacity MW | H4: Energy MWh | I4: Storage Hours | J4: Dispatch Condition | K4: Minimum PLF % | L4: EMD | M4: BG / PBG Conditions | N4: Bid Submission Date | O4: Opening Date | P4: PPA Tenure Years | Q4: Confidence % | R4: Extracted On | S4: Review Status

Sheet Change Review
A1: Tender Change & Corrigendum Review Queue
A3: Proposed changes are generated by comparing the current tender record with newly scanned pages or documents. Approve before applying.
A5: Review ID | B5: Tender ID | C5: Agency | D5: Tender Number | E5: Change Source | F5: Field | G5: Current Value | H5: Proposed Value | I5: Change Type | J5: Confidence % | K5: Detected On | L5: Decision | M5: Reviewer Notes | N5: Source URL | O5: Applied On | P5: Apply Result

Sheet Tender Snapshots
A1: Tender Snapshot Registry
A4: Snapshot ID | B4: Tender ID | C4: Agency | D4: Tender Number | E4: Captured On | F4: Source Type | G4: Source URL | H4: Status | I4: Submission Date | J4: Corrigendum Count | K4: Fingerprint | L4: Raw Snapshot File

Sheet Import Control
A1: Automated Import & Write-Back Control
A3: Use connector CSV/JSON outputs as import batches. Validation and duplicate checks occur before records are written to Master Tenders.
A5: Import Setting | B5: Value | C5: Description | D5: Required
A6: Import folder | B6: imports | C6: Folder containing connector output files | D6: Yes
A7: Archive folder | B7: archive | C7: Processed files are moved here | D7: Yes
A8: Rejected folder | B8: rejected | C8: Invalid files and rows | D8: Yes
A9: Supported formats | B9: CSV, JSON | C9: CSV or JSON array records | D9: Yes
A10: Duplicate policy | B10: Update existing | C10: Skip or update matching Agency + Tender Number | D10: Yes
A11: Apply approved reviews | B11: Yes | C11: Apply Change Review rows marked Approve | D11: Yes
A14: Batch ID | B14: File Name | C14: File Type | D14: Agency | E14: Received On | F14: Records Read | G14: Valid | H14: Rejected | I14: New | J14: Updated | K14: Review Items | L14: Batch Status

Sheet Validation Errors
A1: Import Validation Errors
A4: Error ID | B4: Batch ID | C4: Row Number | D4: Agency | E4: Tender Number | F4: Field | G4: Invalid Value | H4: Validation Rule | I4: Severity | J4: Resolution | K4: Notes

Sheet Writeback Audit
A1: Master Database Write-Back Audit
A4: Audit ID | B4: Timestamp | C4: Operation | D4: Tender ID | E4: Agency | F4: Tender Number | G4: Source Batch / Review | H4: Field | I4: Old Value | J4: New Value | K4: Result | L4: Workbook Row | M4: Notes

Sheet Agency Coverage
A1: Agency Connector Coverage Roadmap
A4: Category | B4: Agency | C4: Connector Type | D4: Version Added | E4: Live Ready | F4: PDF Support | G4: Change Detection | H4: Status / Notes
A5: Central | B5: SECI | C5: Dedicated HTML | D5: V3 | E5: Yes | F5: Yes | G5: Yes | H5: Ready for layout testing
A6: Central | B6: NTPC REL | C6: Dedicated HTML | D6: V3 | E6: Yes | F6: Yes | G6: Yes | H6: Ready for layout testing
A7: Central | B7: NHPC | C7: Dedicated HTML/PDF | D7: V4 | E7: Partial | F7: Yes | G7: Yes | H7: Needs page-selector tuning
A8: Central | B8: SJVN | C8: Dedicated HTML/PDF | D8: V4 | E8: Partial | F8: Yes | G8: Yes | H8: Needs page-selector tuning
A9: Rajasthan | B9: RUVNL | C9: Generic + configurable selectors | D9: V5 | E9: Partial | F9: Yes | G9: Yes | H9: State connector module added
A10: Karnataka | B10: KREDL | C10: Generic + configurable selectors | D10: V5 | E10: Partial | F10: Yes | G10: Yes | H10: State connector module added
A11: Madhya Pradesh | B11: MPUVNL | C11: Generic + configurable selectors | D11: V5 | E11: Partial | F11: Yes | G11: Yes | H11: State connector module added
A12: Maharashtra | B12: MSEDCL | C12: Planned | D12: V6 | E12: No | F12: Planned | G12: Planned
A13: Gujarat | B13: GUVNL | C13: Planned | D13: V6 | E13: No | F13: Planned | G13: Planned
A14: Odisha | B14: GRIDCO | C14: Planned | D14: V6 | E14: No | F14: Planned | G14: Planned
A15: Punjab | B15: PSPCL | C15: Planned | D15: V6 | E15: No | F15: Planned | G15: Planned
A16: Uttar Pradesh | B16: UPNEDA | C16: Planned | D16: V6 | E16: No | F16: Planned | G16: Planned
A17: Maharashtra | B17: MSEDCL | C17: Configurable HTML/PDF | D17: V6 | E17: Partial | F17: Yes | G17: Yes | H17: Connector module added
A18: Gujarat | B18: GUVNL | C18: Configurable HTML/PDF | D18: V6 | E18: Partial | F18: Yes | G18: Yes | H18: Connector module added
A19: Odisha | B19: GRIDCO | C19: Configurable HTML/PDF | D19: V6 | E19: Partial | F19: Yes | G19: Yes | H19: Connector module added
A20: Punjab | B20: PSPCL | C20: Configurable HTML/PDF | D20: V6 | E20: Partial | F20: Yes | G20: Yes | H20: Connector module added

Sheet Execution Control
A1: Execution, Backup & Workbook Write-Back Control
A3: Version 6 supports direct modification of the workbook by the packaged Python engine, with pre-write backup and detailed run reporting.
A5: Execution Setting | B5: Value | C5: Purpose | D5: Recommended
A6: Workbook file | B6: Renewable_Tender_Tracker_V6.xlsx | C6: Target workbook | D6: Yes
A7: Backup folder | B7: backups | C7: Pre-write copies | D7: Yes
A8: Import folder | B8: imports | C8: Connector/import files | D8: Yes
A9: Output folder | B9: output | C9: Logs and reports | D9: Yes
A10: Write mode | B10: Approved + validated | C10: Controls data written | D10: Yes
A11: Dry run | B11: Yes | C11: Test without changing workbook | D11: Yes initially
A12: Create backup | B12: Yes | C12: Required before live writes | D12: Yes
A13: Apply approved reviews | B13: Yes | C13: Updates approved review queue | D13: Yes
A14: Recalculate derived fields | B14: Yes | C14: Refresh formula-driven fields | D14: Yes
A15: Archive input files | B15: Yes | C15: Moves processed files | D15: Yes
A18: Execution ID | B18: Started | C18: Finished | D18: Mode | E18: Input Files | F18: Rows Read | G18: Inserted | H18: Updated | I18: Skipped | J18: Reviews Applied | K18: Errors | L18: Backup File

Sheet Management Report
A1: Renewable Tender Management Report
A3: Executive summary generated from the Master Tenders database.
A5: KPI | B5: Value | D5: Technology | E5: Capacity MW | G5: Status | H5: Count
A6: Total records | B6: =COUNTA('Master Tenders'!A2:A17) | D6: Solar | E6: =SUMIFS('Master Tenders'!G:G,'Master Tenders'!F:F,"Solar") | G6: New | H6: =COUNTIF('Master Tenders'!Q:Q,"New")
A7: Open / Extended | B7: =COUNTIF('Master Tenders'!Q2:Q17,"Open")+COUNTIF('Master Tenders'!Q2:Q17,"Extended") | D7: Solar + BESS | E7: =SUMIFS('Master Tenders'!G:G,'Master Tenders'!F:F,"Solar + BESS") | G7: Open | H7: =COUNTIF('Master Tenders'!Q:Q,"Open")
A8: New tenders | B8: =COUNTIF('Master Tenders'!Q2:Q17,"New") | D8: FDRE | E8: =SUMIFS('Master Tenders'!G:G,'Master Tenders'!F:F,"FDRE") | G8: Extended | H8: =COUNTIF('Master Tenders'!Q:Q,"Extended")
A9: Corrigenda | B9: =COUNTIF('Master Tenders'!Q2:Q17,"Corrigendum") | D9: Wind | E9: =SUMIFS('Master Tenders'!G:G,'Master Tenders'!F:F,"Wind") | G9: Corrigendum | H9: =COUNTIF('Master Tenders'!Q:Q,"Corrigendum")
A10: Closing in 7 days | B10: =COUNTIFS('Master Tenders'!N2:N17,">="&TODAY(),'Master Tenders'!N2:N17,"<="&TODAY()+7) | D10: Hybrid | E10: =SUMIFS('Master Tenders'!G:G,'Master Tenders'!F:F,"Hybrid") | G10: Closed | H10: =COUNTIF('Master Tenders'!Q:Q,"Closed")
A11: Total capacity MW | B11: =SUM('Master Tenders'!G2:G17) | D11: BESS | E11: =SUMIFS('Master Tenders'!G:G,'Master Tenders'!F:F,"BESS") | G11: Cancelled | H11: =COUNTIF('Master Tenders'!Q:Q,"Cancelled")
A12: Storage-linked MW | B12: =SUMIFS('Master Tenders'!G2:G17,'Master Tenders'!H2:H17,"Yes") | D12: Pumped Storage | E12: =SUMIFS('Master Tenders'!G:G,'Master Tenders'!F:F,"Pumped Storage") | G12: Awarded | H12: =COUNTIF('Master Tenders'!Q:Q,"Awarded")
A13: Agencies represented | B13: =COUNTA(UNIQUE(FILTER('Master Tenders'!C2:C17,'Master Tenders'!C2:C17<>""))) | D13: RTC | E13: =SUMIFS('Master Tenders'!G:G,'Master Tenders'!F:F,"RTC") | G13: Expired but Open | H13: =COUNTIFS('Master Tenders'!X:X,"Expired",'Master Tenders'!Q:Q,"Open")

Sheet Daily Summary
A1: Daily Tender Update Summary
A4: Update Date | B4: New Tenders | C4: Updated Tenders | D4: Corrigenda | E4: Extensions | F4: Closures | G4: Errors | H4: Active Capacity MW | I4: Urgent Deadlines | J4: Agencies Scanned | K4: Notes

Sheet V7 Snapshot Coverage
A1: V8 Live Snapshot Coverage — 02 August 2026
A4: Agency | B4: Records Populated | C4: Official Page Reached | D4: Deadline Available | E4: Technical Fields Available | F4: Portal Restriction | G4: Current Result | H4: Next Action
A5: SECI | B5: 7 | C5: Yes | D5: Yes | E5: Partial / detail pages | F5: No | G5: Populated | H5: Parse all RfS PDFs
A6: NTPC REL | B6: 5 | C6: Yes | D6: Yes | E6: Capacity, storage and EMD | F6: No | G6: Populated | H6: Expand active NIT search
A7: NHPC | B7: 5 | C7: Yes | D7: Partial | E7: Detailed capacity/storage/dispatch | F7: Some CPPP documents expire | G7: Populated | H7: Confirm latest deadlines for corrigendum-only records
A8: SJVN | B8: 2 | C8: Yes | D8: Yes | E8: Title-level, some capacity | F8: No | G8: Populated | H8: Open individual tender details
A9: MPUVNL | B9: 2 | C9: Yes | D9: Yes on one record | E9: EMD and dates available | F9: Document download may expire | G9: Populated | H9: Search active tender list for newer RE records
A10: MSEDCL | B10: 1 | C10: Yes | D10: Not on listing | E10: Title-level | F10: No | G10: Populated as corrigendum | H10: Open RfS/corrigendum documents
A11: GRIDCO | B11: 2 | C11: Yes | D11: Partial | E11: Capacity and storage on selected records | F11: No | G11: Populated | H11: Separate current and archive listings
A12: PSPCL | B12: 1 | C12: Yes | D12: Not visible | E12: Title-level | F12: No | G12: Populated as EOI/corrigendum | H12: Open EOI PDF
A13: Jodhpur VVNL | B13: 1 | C13: Yes | D13: Yes | E13: Title and dates | F13: Historical record | G13: Populated | H13: Search current PM-KUSUM tenders
A14: Karnataka agencies | B14: 0 | C14: Portal reached | D14: Portal search required | E14: No extracted record | F14: KPPP organisation filters | G14: Manual verification | H14: Search KPPP by agency
A15: AP / Telangana / Tamil Nadu | B15: 0 | C15: Partial | D15: No | E15: No | F15: Multiple portals | G15: Manual verification | H15: Portal-by-portal inspection
A16: UPNEDA / BSPHCL / HAREDA | B16: 0 | C16: Partial | D16: No | E16: No | F16: Indexing / portal limits | G16: Manual verification | H16: Portal-by-portal inspection

Sheet Manual Verification Queue
A1: Agencies Requiring Manual or Portal Verification
A4: Priority | B4: Category | C4: Agency | D4: Likely Portal | E4: Reason Not Populated | F4: Required Action | G4: Last Attempt | H4: Status | I4: Owner | J4: Notes
A5: High | B5: Central | C5: NHPC | D5: NHPC official tenders / CPPP | E5: No current RE-specific rows reliably indexed | F5: Inspect official tender listings and PDFs | G5: 46236 | H5: Pending
A6: High | B6: Rajasthan | C6: RUVNL / RVPN | D6: Rajasthan eProcurement | E6: Tender data not reliably indexed | F6: Search state portal by organisation and RE keywords | G6: 46236 | H6: Pending
A7: High | B7: Karnataka | C7: KREDL / KPTCL / KPCL | D7: Karnataka Public Procurement Portal | E7: Tender pages may require portal navigation | F7: Search solar, wind, BESS and hybrid keywords | G7: 46236 | H7: Pending
A8: High | B8: Madhya Pradesh | C8: MPUVNL / MPPMCL | D8: MP eProcurement | E8: Portal-specific search required | F8: Search by agency and procurement category | G8: 46236 | H8: Pending
A9: Medium | B9: Andhra Pradesh | C9: APSPDCL / APGENCO / NREDCAP | D9: AP eProcurement | E9: Multiple agency portals | F9: Search tender and procurement pages | G9: 46236 | H9: Pending
A10: Medium | B10: Telangana | C10: TGNPDCL / TSSPDCL | D10: Telangana eProcurement | E10: Multiple agency portals | F10: Search RE procurement notices | G10: 46236 | H10: Pending
A11: Medium | B11: Tamil Nadu | C11: TNGECL / TANTRANSCO | D11: Tamil Nadu tenders portal | E11: Portal and organisation filters required | F11: Search BESS, solar, wind and RTC | G11: 46236 | H11: Pending
A12: Medium | B12: Haryana | C12: HAREDA | D12: Haryana eProcurement | E12: No current indexed result located | F12: Search official portal and notices | G12: 46236 | H12: Pending
A13: Medium | B13: Uttar Pradesh | C13: UPNEDA | D13: UP eTender | E13: No current indexed result located | F13: Search official portal and notices | G13: 46236 | H13: Pending
A14: Medium | B14: Bihar | C14: BSPHCL | D14: Bihar eProcurement | E14: No current indexed result located | F14: Search official portal and notices | G14: 46236 | H14: Pending

Sheet Current Opportunities
A1: Current Utility-Scale Power Procurement Tenders
A3: Supply, installation, EPC, turnkey and O&M-only tenders are excluded. Detailed supply and penalty clauses are maintained on each Master row.
A5: Tender ID | B5: Category | C5: Agency | D5: State | E5: Tender Number | F5: Technology | G5: Capacity MW | H5: Storage Required | I5: Storage Hours | J5: Dispatch Condition | K5: Minimum PLF % | L5: EMD | M5: BG / PBG Conditions | N5: Bid Submission Date | O5: Technical Opening | P5: Financial Opening | Q5: Status | R5: Last Updated | S5: Corrigendum Count | T5: Tender URL | U5: Document URL | V5: Remarks | W5: Days to Deadline | X5: Deadline Alert | Y5: Duplicate Key | Z5: Duplicate Flag | AA5: Change Fingerprint | AB5: Verified On | AC5: Source Quality | AD5: Data Completeness | AE5: Evidence Score | AF5: Opportunity Class | AG5: Tender Notification Date | AH5: Corrigendum Date(s) | AI5: Latest Corrigendum Date | AJ5: Corrigendum Details | AK5: Procurement Model | AL5: Supply Window / Dispatch Selection | AM5: Daily Supply Obligation | AN5: Monthly Minimum / Reconciliation | AO5: Annual PLF / CUF / Energy Requirement | AP5: Allowed Shortfall / Availability Tolerance | AQ5: Under-Supply Penalty | AR5: External / Exchange Energy Allowed | AS5: Maximum External Energy | AT5: Charging / External Energy Conditions | AU5: Third-Party / Merchant Use | AV5: Detailed Source Document | AW5: Technical Review Status
A6: {=_xlfn._xlws.FILTER('Master Tenders'!A2:AW5,'Master Tenders'!A2:A5<>"","No eligible procurement tenders")} | B6: Central | C6: SECI | D6: All India | E6: SECI/C&P/IPP/13/0002/26-27 | F6: FDRE | G6: 500 | H6: Yes | I6: 2 | J6: Assured peak supply under CfD | K6: 0 | L6: As per RfS | M6: As per RfS | N6: 46237.75 | O6: 0 | P6: 46240.417 | Q6: Open | R6: 46236 | S6: 0 | T6: https://www.seci.co.in/tenders/ | U6: 0 | V6: 1000 MWh = 500 MW x 2 hours | W6: 1.75 | X6: Urgent | Y6: SECI|SECI/C&P/IPP/13/0002/26-27 | Z6: Unique | AA6: SECI|SECI/C&P/IPP/13/0002/26-27|20260803|Open|0|20260717 | AB6: 46236 | AC6: Official agency page | AD6: Core fields | AE6: 5 | AF6: Current Opportunity | AG6: 46131 | AH6: 2026-07-17 | AI6: 46220 | AJ6: Amendment-01 uploaded 17-Jul-2026; revised RfS dated 15-Jul-2026 | AK6: Contract for Difference (CfD); power sold through exchanges | AL6: RPD chooses any 2 hours daily between 18:00 and 24:00, within non-solar hours | AM6: 2 MWh per MW contracted capacity per day; for 500 MW = 1,000 MWh/day | AN6: No monthly PLF stated. Performance tested weekly; penalties recovered monthly | AO6: 100% of annual scheduled energy must be renewable. No annual PLF/CUF percentage stated | AP6: Up to 10% weekly shortfall permitted; minimum 90% of 14 MWh/MW per contract week | AQ6: Beyond 10% weekly shortfall: 1.5 × [highest applicable exchange MCP during non-solar hours minus strike price] × shortfall; no penalty when reference rate is below strike price; no CfD settlement for shortfall | AR6: Yes — green-market sources or bilateral RE agreements permitted | AS6: Up to 25% of total annual required energy | AT6: External RE can directly meet peak supply or charge ESS. Charging energy is not counted; only discharged energy counts. External-energy excess above 25% receives no CfD settlement | AU6: ESS may be used for merchant/third-party or exchange sale after completing the day’s 2 MWh/MW peak obligation; premature merchant sale attracts an additional penalty | AV6: https://www.seci.co.in/uploads/tenders/Revised_RfS_for_1000_MWh_assured_Peak_Supply_under_CfD_Mechanism_%28CfD-I%29.pdf | AW6: Verified from revised official RfS
A7: SECI000258 | B7: Central | C7: SECI | D7: All India | E7: SECI/C&P/IPP/13/0006/26-27 | F7: FDRE | G7: 1200 | H7: Yes | I7: 4 | J7: Assured peak supply | K7: 0 | L7: As per RfS | M7: As per RfS | N7: 46241.75 | O7: 0 | P7: 46246.417 | Q7: Extended | R7: 46236 | S7: 1 | T7: https://www.seci.co.in/tender-details/Ymd_ | U7: 0 | V7: Amendment-01 listed; online deadline passed, offline date 04-Aug-2026 | W7: 5.75 | X7: Due in 7 Days | Y7: SECI|SECI/C&P/IPP/13/0006/26-27 | Z7: Unique | AA7: SECI|SECI/C&P/IPP/13/0006/26-27|20260807|Extended|1|20260708 | AB7: 46236 | AC7: Official agency page | AD7: Core fields | AE7: 5 | AF7: Current Opportunity | AG7: 46178 | AH7: 2026-07-08 | AI7: 46211 | AJ7: Amendment-01 uploaded 08-Jul-2026 | AK7: Tariff-based competitive bidding with PPA/PSA | AL7: Buying Entity selects 4 hours daily across evening-to-next-morning non-solar peak hours; at least one continuous hour | AM7: 4 MWh per MW contracted capacity per day; for 1,200 MW = 4,800 MWh/day | AN7: Monthly reconciliation. Minimum effective supply = 90% of monthly scheduled peak-energy requirement before penalty applies | AO7: 100% annual offered energy must be renewable. No annual PLF/CUF percentage stated | AP7: Monthly shortfall up to 10% below required peak energy permitted | AQ7: Shortfall beyond 10% monthly: 1.5 × PPA tariff × energy shortfall | AR7: Yes — green-market sources or bilateral RE agreements permitted | AS7: Up to 5% of total annual required energy | AT7: External RE may directly meet peak requirements or charge ESS. Only discharged ESS energy counts toward the 5%; excess above 5% is unpaid and excluded from performance | AU7: ESS may be used outside peak hours for third-party/exchange sale after PPA obligations. Sale before fulfilling obligations attracts 1.5 × highest DAM/GDAM/RTM market rate per kWh, in addition to shortfall penalty | AV7: https://www.seci.co.in/uploads/tenders/RfS_for_4800_MWh_Peak_Supply_%28FDRE-IX%29-_final_upload.pdf | AW7: Verified from official RfS; latest SECI page shows revised bid dates
A8: SJVN-BESS2 | B8: Central | C8: SJVN | D8: Haryana | E8: SJVN/CCDelhi/REIA/2026/BESS-2 | F8: BESS | G8: 265 | H8: Yes | I8: 2 | J8: Standalone BESS under VGF and TBCB | K8: 0 | L8: 0 | M8: As per RfS | N8: 46255 | O8: 0 | P8: 0 | Q8: Open | R8: 46236 | S8: 0 | T8: https://sjvn.nic.in/en/tender | U8: 0 | V8: 265 MW / 530 MWh BESS in Haryana | W8: 19 | X8: Normal | Y8: SJVN|SJVN/CCDELHI/REIA/2026/BESS-2 | Z8: Unique | AA8: SJVN|SJVN/CCDelhi/REIA/2026/BESS-2|20260821|Open|0| | AB8: 46236 | AC8: Official agency page | AD8: Core fields | AE8: 5 | AF8: Current Opportunity | AG8: 46227 | AH8: 0 | AI8: 0 | AJ8: No corrigendum identified in the captured official listing. | AK8: Standalone BESS under VGF and tariff-based competitive bidding | AL8: Dispatch schedule and availability obligations governed by RfS/BESSA/BESPA | AM8: Not verified from accessible document text | AN8: PLF is not applicable to standalone BESS; monthly availability/energy obligations require document review | AO8: Annual PLF/CUF not applicable; annual availability/cycle obligations require document review | AP8: Not verified from accessible document text | AQ8: Not verified from accessible document text | AR8: Charging-source provision not verified from accessible document text | AS8: Not verified | AT8: Official RfS PDF was listed but could not be reliably fetched in this review | AU8: Merchant-use rights not verified | AV8: https://sjvn.nic.in/sites/default/files/2026-07/RfS%20BESS%202%20240726.pdf | AW8: Document-level review pending; no assumptions inserted
A9: MSEDCL-BESS-2000 | B9: Maharashtra | C9: MSEDCL | D9: Maharashtra | E9: RfS-2000MW-4000MWh-BESS-2026 | F9: BESS | G9: 2000 | H9: Yes | I9: 2 | J9: Tariff-based competitive bidding | K9: 0 | L9: 0 | M9: As per RfS | N9: 0 | O9: 0 | P9: 0 | Q9: Corrigendum | R9: 46236 | S9: 2 | T9: https://www.mahadiscom.in/en/supplier/tenders/ | U9: 0 | V9: Corrigendum-2 published 22-Jul-2026; deadline not visible on listing | Y9: MSEDCL|RFS-2000MW-4000MWH-BESS-2026 | Z9: Unique | AA9: MSEDCL|RfS-2000MW-4000MWh-BESS-2026||Corrigendum|2|20260722 | AB9: 46236 | AC9: Official agency page | AD9: Partial | AE9: 4 | AF9: Needs Status Check | AG9: 46203 | AH9: 2026-07-07; 2026-07-22 | AI9: 46225 | AJ9: Addendum-1 and Addendum-2 published 07-Jul-2026; Corrigendum-2 published 22-Jul-2026 | AK9: Standalone BESS under tariff-based competitive bidding | AL9: Dispatch/charging schedule governed by RfS and BESPA | AM9: PLF is not applicable to standalone BESS; daily cycle and availability obligations require current 2026 RfS review | AN9: Monthly availability/payment condition not verified from accessible current document text | AO9: Annual PLF/CUF not applicable; annual availability requirement not verified | AP9: Not verified from accessible current 2026 document text | AQ9: Not verified from accessible current 2026 document text | AR9: Charging source and grid/exchange charging permission not verified | AS9: Not verified | AT9: Current 2026 tender and corrigenda are visible on MSEDCL, but detailed clauses require opening the RfS/corrigendum PDF | AU9: Merchant-use rights not verified | AV9: https://www.mahadiscom.in/en/supplier/tenders/ | AW9: Tender confirmed; commercial clause extraction pending

Sheet Source Evidence
A1: Official Source Evidence Register
A4: Evidence ID | B4: Agency | C4: Tender ID / Reference | D4: Official URL | E4: Evidence Captured | F4: Verified Facts | G4: Evidence Level | H4: Notes
A5: EV-NHPC-01 | B5: NHPC | C5: 2025_NHPC_849236_1 | D5: https://www.nhpcindia.com/welcome/tender_detail/7841.html | E5: 46236 | F5: 500 MW / 1000 MWh; Andhra Pradesh; 2-hour; peak use; corrigenda | G5: High | H5: Official NHPC detail page
A6: EV-NHPC-02 | B6: NHPC | C6: 2025_NHPC_849707_1 | D6: https://eprocure.gov.in/eprocure/app | E6: 46236 | F6: 1200 MW solar; 600 MW / 2400 MWh ESS; corrigendum | G6: High | H6: Official CPPP record
A7: EV-NHPC-03 | B7: NHPC | C7: 2025_NHPC_844873_1 | D7: https://www.nhpcindia.com/welcome/tender_detail/7738.html | E7: 46236 | F7: 125 MW / 500 MWh Kerala BESS; six corrigenda | G7: High | H7: Official NHPC detail page
A8: EV-MP-01 | B8: MPUVNL | C8: 2026_MPUVN_484501_1 | D8: https://mptenders.gov.in/nicgep/app | E8: 46236 | F8: Rooftop solar RESCO; eight districts; EMD 184000; bid dates | G8: High | H8: Official MP eProcurement
A9: EV-MP-02 | B9: MPUVNL | C9: 2026_MPUVN_511408_1 | D9: https://mptenders.gov.in/nicgep/app | E9: 46236 | F9: Solar cooker tender under technical evaluation | G9: Medium | H9: Status page only
A10: EV-RAJ-01 | B10: Jodhpur VVNL | C10: 2025_JdVVN_455300_1 | D10: https://eproc.rajasthan.gov.in/nicgep/app | E10: 46236 | F10: PM-KUSUM RESCO solar; Nohar/Sangaria; extension dates | G10: High | H10: Official Rajasthan eProcurement

Sheet Exclusion Log
A1: Tender Exclusion Log
A3: Excluded automatically under the configured scope: capacity below 100 MW, unconfirmed capacity, rooftop solar, or PM-KUSUM.
A5: Tender ID | B5: Agency | C5: Tender Number | D5: Technology | E5: Capacity MW | F5: Status | G5: Exclusion Reason | H5: Source URL
A6: SECI000265 | B6: SECI | C6: SECI/C&P/IPP/11/0007/26-27 | D6: Solar | E6: 5.29 | F6: Open | G6: Rooftop solar excluded; Capacity below 100 MW | H6: https://www.seci.co.in/tender-details/YmRy
A7: SECI000264 | B7: SECI | C7: SECI/C&P/EOI/17/0002/26-27 | D7: Other | F7: Open | G7: Capacity not confirmed | H7: https://www.seci.co.in/tenders/
A8: SECI000263 | B8: SECI | C8: SECI/C&P/OP/11/0003/26-27 | D8: Wind | E8: 45.6 | F8: Open | G8: Capacity below 100 MW | H8: https://www.seci.co.in/tender-details/YmR0
A9: SECI000252 | B9: SECI | C9: SECI/C&P/OP/11/0001/26-27 | D9: Solar | E9: 88 | F9: Open | G9: Capacity below 100 MW | H9: https://www.seci.co.in/tender-details/Ymd1
A10: SECI000262 | B10: SECI | C10: SECI/C&P/OP/11/0002/26-27 | D10: Solar + BESS | E10: 70 | F10: Open | G10: Capacity below 100 MW | H10: https://www.seci.co.in/tenders/
A11: GRIDCO-FSPV-2026 | B11: GRIDCO | C11: GRIDCO/RE NODAL AGENCY/E-TENDER/01/2026-27 | D11: Solar | F11: Open | G11: Capacity not confirmed | H11: https://www.gridco.co.in/archive_tender.aspx
A12: PSPCL-BIOMASS-65 | B12: PSPCL | C12: 65/Elec-H&CG-92 | D12: Other | F12: Corrigendum | G12: Capacity not confirmed | H12: https://pspcl.in/renewable-purchase-obligation-circulars/Expression-of-interest
A13: MPUVNL-484501 | B13: MPUVNL | C13: 2026_MPUVN_484501_1 | D13: Solar | F13: Closed | G13: Rooftop solar excluded; Capacity not confirmed | H13: https://mptenders.gov.in/nicgep/app
A14: MPUVNL-511408 | B14: MPUVNL | C14: 2026_MPUVN_511408_1 | D14: Other | F14: Evaluation | G14: Capacity not confirmed | H14: https://mptenders.gov.in/nicgep/app
A15: JDVVNL-KUSUM-100 | B15: Jodhpur VVNL | C15: 2025_JdVVN_455300_1 | D15: Solar | F15: Closed | G15: PM-KUSUM excluded; Capacity not confirmed | H15: https://eproc.rajasthan.gov.in/nicgep/app
A16: NTPC29973 | B16: NTPC REL | C16: NREL-CS-5824-004(BESS1)-9 | D16: BESS | E16: 240 | F16: Closed | G16: Closed/expired as of 2026-08-02 | H16: https://ntpctender.ntpc.co.in/NITDetails/NITs/29973
A17: NTPC29990 | B17: NTPC REL | C17: NRE-CS-5820-004(EPC)-9 | D17: Solar | E17: 600 | F17: Closed | G17: Closed/expired as of 2026-08-02 | H17: https://ntpctender.ntpc.co.in/NITDetails/NITs/29990
A18: NTPC29893 | B18: NTPC REL | C18: NRE-CS-5846-004(PHES)-9 | D18: Pumped Storage | E18: 2000 | F18: Closed | G18: Closed/expired as of 2026-08-02 | H18: https://ntpctender.ntpc.co.in/NITDetails/NITs/29893
A19: NTPC29969 | B19: NTPC REL | C19: NREL-CS-5823-004(BESS1)-9 | D19: BESS | E19: 550 | F19: Closed | G19: Closed/expired as of 2026-08-02 | H19: https://ntpctender.ntpc.co.in/NITDetails/NITs/29969
A20: GRIDCO-BESS-125 | B20: GRIDCO | C20: SECI/C&P/IPP/15/0015/25-26 | D20: BESS | E20: 125 | F20: Closed | G20: Closed/expired as of 2026-08-02 | H20: https://gridco.co.in/archive_tender.aspx/writereaddata/Tenders/repowerghga.aspx
A21: NHPC-849236 | B21: NHPC | C21: 2025_NHPC_849236_1 | D21: BESS | E21: 500 | F21: Closed | G21: Closed/expired as of 2026-08-02 | H21: https://www.nhpcindia.com/welcome/tender_detail/7841.html
A22: NHPC-813414 | B22: NHPC | C22: 2024_NHPC_813414_1 | D22: FDRE | E22: 1200 | F22: Closed | G22: Closed/expired as of 2026-08-02 | H22: https://www.nhpcindia.com/welcome/tender_detail/7140.html
A23: NHPC-835426 | B23: NHPC | C23: 2024_NHPC_835426_1 | D23: Hybrid | E23: 1200 | F23: Closed | G23: Closed/expired as of 2026-08-02 | H23: https://www.nhpcindia.com/welcome/tender_detail/7663.html
A24: NTPC29985 | B24: NTPC REL | C24: NRE-CS-5928-003(WTG)-9 | D24: Wind | E24: 813 | F24: Extended | G24: Supply / installation / EPC / O&M tender excluded | H24: https://ntpctender.ntpc.co.in/NITDetails/NITs/29985
A25: SJVN-GEM7789243 | B25: SJVN | C25: GEM/2026/B/7789243 | D25: Solar | E25: 200 | F25: Open | G25: Supply / installation / EPC / O&M tender excluded | H25: https://www.sjvn.nic.in/en/tender?page=2
A26: NHPC-849707 | B26: NHPC | C26: 2025_NHPC_849707_1 | D26: Solar + BESS | E26: 1200 | F26: Corrigendum | G26: Official bid deadline expired in 2025 | H26: https://eprocure.gov.in/eprocure/app
A27: NHPC-844873 | B27: NHPC | C27: 2025_NHPC_844873_1 | D27: BESS | E27: 125 | F27: Corrigendum | G27: Official bid deadline expired in 2025 | H27: https://www.nhpcindia.com/welcome/tender_detail/7738.html
A28: SECI000265 | B28: SECI | C28: SECI/C&P/IPP/11/0007/26-27 | D28: Solar | F28: Open | G28: Rooftop solar excluded | H28: https://www.seci.co.in/tender-details/YmRy
A29: SECI000264 | B29: SECI | C29: SECI/C&P/EOI/17/0002/26-27 | D29: Other | F29: Open | G29: Capacity not confirmed | H29: https://www.seci.co.in/tender-details/YmRz
A30: SECI000263 | B30: SECI | C30: SECI/C&P/OP/11/0003/26-27 | D30: Wind | E30: 45.6 | F30: Open | G30: Capacity below configured minimum | H30: https://www.seci.co.in/tender-details/YmR0
A31: SECI000252 | B31: SECI | C31: SECI/C&P/OP/11/0001/26-27 | D31: Solar | E31: 88 | F31: Open | G31: EPC / turnkey / BoS excluded | H31: https://www.seci.co.in/tender-details/Ymd1
A32: SECI000262 | B32: SECI | C32: SECI/C&P/OP/11/0002/26-27 | D32: Solar + BESS | E32: 25 | F32: Open | G32: Capacity below configured minimum | H32: https://www.seci.co.in/tender-details/YmR1
B33: NTPC REL | D33: Wind | E33: 813 | F33: Corrigendum | G33: Supply / installation excluded | H33: https://ntpctender.ntpc.co.in/NITDetails/NITs/29708
B34: GRIDCO | C34: View Details Tender Document Addendum-I Pre-Bid Meeting Link Corrigendum-II Addendum-6 Odisha Floating Solar Data Room - Contents Addendum_09 Addendum | D34: Solar | F34: Corrigendum | G34: Capacity not confirmed | H34: https://www.gridco.co.in/writereaddata/Tenders/301225101225upload.pdf
B35: GRIDCO | C35: Addendum-6 Odisha Floating Solar Data Room - Contents | D35: Solar | F35: Open | G35: Capacity not confirmed | H35: https://www.gridco.co.in/writereaddata/Tenders/301126051106Addendum-6_Odisha Floating Solar Data room - Contents.pdf
A36: SECI000267 | B36: SECI | C36: SECI/C&P/MI/00/0001/26-27 | D36: Other | F36: Open | G36: Capacity not confirmed | H36: https://www.seci.co.in/tender-details/YmRw
A37: SECI000265 | B37: SECI | C37: SECI/C&P/IPP/11/0007/26-27 | D37: Solar | F37: Open | G37: Rooftop solar excluded | H37: https://www.seci.co.in/tender-details/YmRy
A38: SECI000264 | B38: SECI | C38: SECI/C&P/EOI/17/0002/26-27 | D38: Other | F38: Open | G38: Capacity not confirmed | H38: https://www.seci.co.in/tender-details/YmRz
A39: SECI000263 | B39: SECI | C39: SECI/C&P/OP/11/0003/26-27 | D39: Wind | E39: 45.6 | F39: Open | G39: Capacity below configured minimum | H39: https://www.seci.co.in/tender-details/YmR0
A40: SECI000252 | B40: SECI | C40: SECI/C&P/OP/11/0001/26-27 | D40: Solar | E40: 88 | F40: Open | G40: EPC / turnkey / BoS excluded | H40: https://www.seci.co.in/tender-details/Ymd1
A41: SECI000262 | B41: SECI | C41: SECI/C&P/OP/11/0002/26-27 | D41: Solar + BESS | E41: 25 | F41: Open | G41: Capacity below configured minimum | H41: https://www.seci.co.in/tender-details/YmR1
B42: GRIDCO | C42: View Details Tender Document Addendum-I Pre-Bid Meeting Link Corrigendum-II Addendum-6 Odisha Floating Solar Data Room - Contents Addendum_09 Addendum | D42: Solar | F42: Corrigendum | G42: Capacity not confirmed | H42: https://www.gridco.co.in/writereaddata/Tenders/301225101225upload.pdf
B43: GRIDCO | C43: Addendum-6 Odisha Floating Solar Data Room - Contents | D43: Solar | F43: Open | G43: Capacity not confirmed | H43: https://www.gridco.co.in/writereaddata/Tenders/301126051106Addendum-6_Odisha Floating Solar Data room - Contents.pdf
A44: SECI000249 | B44: SECI | C44: SECI/C&P/IPP/13/0002/26-27 | D44: FDRE | E44: 500 | F44: Open | G44: Deadline expired without verified extension | H44: https://www.seci.co.in/tenders/
A45: SECI000267 | B45: SECI | C45: SECI/C&P/MI/00/0001/26-27 | D45: Other | F45: Open | G45: Capacity not confirmed | H45: https://www.seci.co.in/tender-details/YmRw
A46: SECI000265 | B46: SECI | C46: SECI/C&P/IPP/11/0007/26-27 | D46: Solar | F46: Open | G46: Rooftop solar excluded | H46: https://www.seci.co.in/tender-details/YmRy
A47: SECI000264 | B47: SECI | C47: SECI/C&P/EOI/17/0002/26-27 | D47: Other | F47: Open | G47: Capacity not confirmed | H47: https://www.seci.co.in/tender-details/YmRz
A48: SECI000263 | B48: SECI | C48: SECI/C&P/OP/11/0003/26-27 | D48: Wind | E48: 45.6 | F48: Open | G48: Capacity below configured minimum | H48: https://www.seci.co.in/tender-details/YmR0
A49: SECI000252 | B49: SECI | C49: SECI/C&P/OP/11/0001/26-27 | D49: Solar | E49: 88 | F49: Open | G49: EPC / turnkey / BoS excluded | H49: https://www.seci.co.in/tender-details/Ymd1
A50: SECI000262 | B50: SECI | C50: SECI/C&P/OP/11/0002/26-27 | D50: Solar + BESS | E50: 25 | F50: Open | G50: Capacity below configured minimum | H50: https://www.seci.co.in/tender-details/YmR1
B51: NTPC REL | D51: Solar | E51: 600 | F51: Corrigendum | G51: EPC / turnkey / BoS excluded | H51: https://ntpctender.ntpc.co.in/NITDetails/NITs/29990
B52: GRIDCO | C52: View Details Tender Document Addendum-I Pre-Bid Meeting Link Corrigendum-II Addendum-6 Odisha Floating Solar Data Room - Contents Addendum_09 Addendum | D52: Solar | F52: Corrigendum | G52: Capacity not confirmed | H52: https://www.gridco.co.in/writereaddata/Tenders/301225101225upload.pdf
B53: GRIDCO | C53: Addendum-6 Odisha Floating Solar Data Room - Contents | D53: Solar | F53: Open | G53: Capacity not confirmed | H53: https://www.gridco.co.in/writereaddata/Tenders/301126051106Addendum-6_Odisha Floating Solar Data room - Contents.pdf
A54: SECI000267 | B54: SECI | C54: SECI/C&P/MI/00/0001/26-27 | D54: Other | F54: Open | G54: Capacity not confirmed | H54: https://www.seci.co.in/tender-details/YmRw
A55: SECI000265 | B55: SECI | C55: SECI/C&P/IPP/11/0007/26-27 | D55: Solar | F55: Open | G55: Rooftop solar excluded | H55: https://www.seci.co.in/tender-details/YmRy
A56: SECI000264 | B56: SECI | C56: SECI/C&P/EOI/17/0002/26-27 | D56: Other | F56: Open | G56: Capacity not confirmed | H56: https://www.seci.co.in/tender-details/YmRz
A57: SECI000263 | B57: SECI | C57: SECI/C&P/OP/11/0003/26-27 | D57: Wind | E57: 45.6 | F57: Open | G57: Capacity below configured minimum | H57: https://www.seci.co.in/tender-details/YmR0
A58: SECI000252 | B58: SECI | C58: SECI/C&P/OP/11/0001/26-27 | D58: Solar | E58: 88 | F58: Open | G58: EPC / turnkey / BoS excluded | H58: https://www.seci.co.in/tender-details/Ymd1
A59: SECI000262 | B59: SECI | C59: SECI/C&P/OP/11/0002/26-27 | D59: Solar + BESS | E59: 25 | F59: Open | G59: Capacity below configured minimum | H59: https://www.seci.co.in/tender-details/YmR1
B60: NTPC REL | D60: Solar | E60: 600 | F60: Corrigendum | G60: EPC / turnkey / BoS excluded | H60: https://ntpctender.ntpc.co.in/NITDetails/NITs/29990
B61: GRIDCO | C61: View Details Tender Document Addendum-I Pre-Bid Meeting Link Corrigendum-II Addendum-6 Odisha Floating Solar Data Room - Contents Addendum_09 Addendum | D61: Solar | F61: Corrigendum | G61: Capacity not confirmed | H61: https://www.gridco.co.in/writereaddata/Tenders/301225101225upload.pdf
B62: GRIDCO | C62: Addendum-6 Odisha Floating Solar Data Room - Contents | D62: Solar | F62: Open | G62: Capacity not confirmed | H62: https://www.gridco.co.in/writereaddata/Tenders/301126051106Addendum-6_Odisha Floating Solar Data room - Contents.pdf
A63: SECI000252 | B63: SECI | C63: SECI/C&P/OP/11/0001/26-27 | D63: Solar | E63: 88 | F63: Open | G63: EPC / turnkey / BoS excluded | H63: https://www.seci.co.in/tender-details/Ymd1
A64: SECI000267 | B64: SECI | C64: SECI/C&P/MI/00/0001/26-27 | D64: Other | F64: Open | G64: Capacity not confirmed | H64: https://www.seci.co.in/tender-details/YmRw
A65: SECI000265 | B65: SECI | C65: SECI/C&P/IPP/11/0007/26-27 | D65: Solar | F65: Open | G65: Rooftop solar excluded | H65: https://www.seci.co.in/tender-details/YmRy
A66: SECI000269 | B66: SECI | C66: SECI000269 | D66: BESS | E66: 40 | F66: Open | G66: Capacity below configured minimum | H66: https://www.seci.co.in/tender-details/YmR-
A67: SECI000264 | B67: SECI | C67: SECI/C&P/EOI/17/0002/26-27 | D67: Other | F67: Open | G67: Capacity not confirmed | H67: https://www.seci.co.in/tender-details/YmRz
A68: SECI000263 | B68: SECI | C68: SECI/C&P/OP/11/0003/26-27 | D68: Wind | E68: 45.6 | F68: Open | G68: Capacity below configured minimum | H68: https://www.seci.co.in/tender-details/YmR0
A69: SECI000262 | B69: SECI | C69: SECI/C&P/OP/11/0002/26-27 | D69: Solar + BESS | E69: 25 | F69: Open | G69: Capacity below configured minimum | H69: https://www.seci.co.in/tender-details/YmR1
B70: NTPC REL | D70: Wind | E70: 813 | F70: Corrigendum | G70: Supply / installation excluded | H70: https://ntpctender.ntpc.co.in/NITDetails/NITs/29985
B71: GRIDCO | C71: View Details Tender Document Addendum-I Pre-Bid Meeting Link Corrigendum-II Addendum-6 Odisha Floating Solar Data Room - Contents Addendum_09 Addendum | D71: Solar | F71: Corrigendum | G71: Capacity not confirmed | H71: https://www.gridco.co.in/writereaddata/Tenders/301225101225upload.pdf
B72: GRIDCO | C72: Addendum-6 Odisha Floating Solar Data Room - Contents | D72: Solar | F72: Open | G72: Capacity not confirmed | H72: https://www.gridco.co.in/writereaddata/Tenders/301126051106Addendum-6_Odisha Floating Solar Data room - Contents.pdf
A73: SECI000270 | B73: SECI | C73: SECI/C&P/OP/15/0005/26-27 | D73: Solar | F73: Open | G73: Rooftop solar excluded | H73: https://www.seci.co.in/tender-details/YmV3
A74: SECI000252 | B74: SECI | C74: SECI/C&P/OP/11/0001/26-27 | D74: Solar | E74: 88 | F74: Open | G74: EPC / turnkey / BoS excluded | H74: https://www.seci.co.in/tender-details/Ymd1
A75: SECI000267 | B75: SECI | C75: SECI/C&P/MI/00/0001/26-27 | D75: Other | F75: Open | G75: Capacity not confirmed | H75: https://www.seci.co.in/tender-details/YmRw
A76: SECI000265 | B76: SECI | C76: SECI/C&P/IPP/11/0007/26-27 | D76: Solar | F76: Open | G76: Rooftop solar excluded | H76: https://www.seci.co.in/tender-details/YmRy
A77: SECI000269 | B77: SECI | C77: SECI000269 | D77: BESS | E77: 40 | F77: Open | G77: Capacity below configured minimum | H77: https://www.seci.co.in/tender-details/YmR-
A78: SECI000262 | B78: SECI | C78: SECI/C&P/OP/11/0002/26-27 | D78: Solar + BESS | E78: 25 | F78: Open | G78: Capacity below configured minimum | H78: https://www.seci.co.in/tender-details/YmR1
A79: SECI000264 | B79: SECI | C79: SECI/C&P/EOI/17/0002/26-27 | D79: Other | F79: Open | G79: Capacity not confirmed | H79: https://www.seci.co.in/tender-details/YmRz
A80: SECI000263 | B80: SECI | C80: SECI/C&P/OP/11/0003/26-27 | D80: Wind | E80: 45.6 | F80: Open | G80: Capacity below configured minimum | H80: https://www.seci.co.in/tender-details/YmR0
B81: NTPC REL | D81: Wind | E81: 813 | F81: Corrigendum | G81: Supply / installation excluded | H81: https://ntpctender.ntpc.co.in/NITDetails/NITs/29985
B82: GRIDCO | C82: View Details Tender Document Addendum-I Pre-Bid Meeting Link Corrigendum-II Addendum-6 Odisha Floating Solar Data Room - Contents Addendum_09 Addendum | D82: Solar | F82: Corrigendum | G82: Capacity not confirmed | H82: https://www.gridco.co.in/writereaddata/Tenders/301225101225upload.pdf
B83: GRIDCO | C83: Addendum-6 Odisha Floating Solar Data Room - Contents | D83: Solar | F83: Open | G83: Capacity not confirmed | H83: https://www.gridco.co.in/writereaddata/Tenders/301126051106Addendum-6_Odisha Floating Solar Data room - Contents.pdf
A84: SECI000258 | B84: SECI | C84: SECI/C&P/IPP/13/0006/26-27 | D84: FDRE | E84: 1500 | F84: Open | G84: Deadline expired without verified extension | H84: https://www.seci.co.in/tender-details/Ymd_
A85: SECI000270 | B85: SECI | C85: SECI/C&P/OP/15/0005/26-27 | D85: Solar | F85: Open | G85: Rooftop solar excluded | H85: https://www.seci.co.in/tender-details/YmV3
A86: SECI000252 | B86: SECI | C86: SECI/C&P/OP/11/0001/26-27 | D86: Solar | E86: 88 | F86: Open | G86: EPC / turnkey / BoS excluded | H86: https://www.seci.co.in/tender-details/Ymd1
A87: SECI000267 | B87: SECI | C87: SECI/C&P/MI/00/0001/26-27 | D87: Other | F87: Open | G87: Capacity not confirmed | H87: https://www.seci.co.in/tender-details/YmRw
A88: SECI000265 | B88: SECI | C88: SECI/C&P/IPP/11/0007/26-27 | D88: Solar | F88: Open | G88: Rooftop solar excluded | H88: https://www.seci.co.in/tender-details/YmRy
A89: SECI000269 | B89: SECI | C89: SECI000269 | D89: BESS | E89: 40 | F89: Open | G89: Capacity below configured minimum | H89: https://www.seci.co.in/tender-details/YmR-
A90: SECI000262 | B90: SECI | C90: SECI/C&P/OP/11/0002/26-27 | D90: Solar + BESS | E90: 25 | F90: Open | G90: Capacity below configured minimum | H90: https://www.seci.co.in/tender-details/YmR1
A91: SECI000264 | B91: SECI | C91: SECI/C&P/EOI/17/0002/26-27 | D91: Other | F91: Open | G91: Capacity not confirmed | H91: https://www.seci.co.in/tender-details/YmRz
A92: SECI000263 | B92: SECI | C92: SECI/C&P/OP/11/0003/26-27 | D92: Wind | E92: 45.6 | F92: Open | G92: Capacity below configured minimum | H92: https://www.seci.co.in/tender-details/YmR0
B93: NTPC REL | D93: Wind | E93: 813 | F93: Corrigendum | G93: Supply / installation excluded | H93: https://ntpctender.ntpc.co.in/NITDetails/NITs/29985
B94: GRIDCO | C94: View Details Tender Document Addendum-I Pre-Bid Meeting Link Corrigendum-II Addendum-6 Odisha Floating Solar Data Room - Contents Addendum_09 Addendum | D94: Solar | F94: Corrigendum | G94: Capacity not confirmed | H94: https://www.gridco.co.in/writereaddata/Tenders/301225101225upload.pdf
B95: GRIDCO | C95: Addendum-6 Odisha Floating Solar Data Room - Contents | D95: Solar | F95: Open | G95: Capacity not confirmed | H95: https://www.gridco.co.in/writereaddata/Tenders/301126051106Addendum-6_Odisha Floating Solar Data room - Contents.pdf
A96: SECI000270 | B96: SECI | C96: SECI/C&P/OP/15/0005/26-27 | D96: Solar | F96: Open | G96: Rooftop solar excluded | H96: https://www.seci.co.in/tender-details/YmV3
A97: SECI000252 | B97: SECI | C97: SECI/C&P/OP/11/0001/26-27 | D97: Solar | E97: 88 | F97: Open | G97: EPC / turnkey / BoS excluded | H97: https://www.seci.co.in/tender-details/Ymd1
A98: SECI000267 | B98: SECI | C98: SECI/C&P/MI/00/0001/26-27 | D98: Other | F98: Open | G98: Capacity not confirmed | H98: https://www.seci.co.in/tender-details/YmRw
A99: SECI000265 | B99: SECI | C99: SECI/C&P/IPP/11/0007/26-27 | D99: Solar | F99: Open | G99: Rooftop solar excluded | H99: https://www.seci.co.in/tender-details/YmRy
A100: SECI000269 | B100: SECI | C100: SECI000269 | D100: BESS | E100: 40 | F100: Open | G100: Capacity below configured minimum | H100: https://www.seci.co.in/tender-details/YmR-
A101: SECI000262 | B101: SECI | C101: SECI/C&P/OP/11/0002/26-27 | D101: Solar + BESS | E101: 25 | F101: Open | G101: Capacity below configured minimum | H101: https://www.seci.co.in/tender-details/YmR1
A102: SECI000264 | B102: SECI | C102: SECI/C&P/EOI/17/0002/26-27 | D102: Other | F102: Open | G102: Capacity not confirmed | H102: https://www.seci.co.in/tender-details/YmRz
...

Sheet Scope Rules
A1: Tender Eligibility Rules
A4: Rule | B4: Value | C4: Effect
A5: Minimum verified capacity MW | B5: 100 | C5: Exclude lower-capacity tenders
A6: Require confirmed capacity | B6: Yes | C6: Exclude blank/unknown capacities
A7: Exclude rooftop solar | B7: Yes | C7: All rooftop/roof-top tenders excluded
A8: Exclude PM-KUSUM | B8: Yes | C8: All KUSUM components excluded
A9: Include utility-scale solar | B9: Yes | C9: Only if capacity ≥100 MW
A10: Include BESS / FDRE / Hybrid | B10: Yes | C10: Only if capacity ≥100 MW
A11: Include historical records | B11: Yes | C11: Kept for reference, classified separately
A13: Active Database Rule | B13: Value | C13: Effect
A14: Retain closed tenders | B14: No | C14: Removed from Master Tenders
A15: Retain expired open tenders | B15: No | C15: Removed when deadline is before scan date
A16: Corrigendum location | B16: Master Tenders | C16: Dates and details remain on the tender row
A17: Notification date required | B17: Yes where verified | C17: Blank when official date is not verified
A19: Procurement Scope Rule | B19: Value | C19: Effect
... A32: Missing detailed clauses | B32: Not verified | C32: No fabricated commercial terms

Sheet Daily Update Setup
A1: Daily Update Operating Model
A4: Step | B4: Process | C4: Runs Where | D4: Result | E4: Manual Action | F4: Recommended Frequency | G4: Status
A5: 1 | B5: Scan official tender pages and configured portals | C5: Cloud runner | D5: Raw tender records | E5: None for accessible sites | F5: Daily | G5: Requires hosting
A6: 2 | B6: Apply eligibility rules | C6: Cloud runner | D6: Rooftop, KUSUM and <100 MW removed | E6: Review exclusions only | F6: Daily | G6: Configured
A7: 3 | B7: Compare with prior workbook | C7: Cloud runner | D7: New/updated/closed/corrigendum changes | E7: Approve uncertain changes | F7: Daily | G7: Framework included
A8: 4 | B8: Download and parse tender PDFs | C8: Cloud runner | D8: PLF, storage, EMD, BG and dates | E8: Review low-confidence fields | F8: Daily | G8: Framework included
A9: 5 | B9: Update workbook and create backup | C9: Cloud runner | D9: New downloadable XLSX | E9: Download latest file | F9: Daily | G9: Framework included
A10: 6 | B10: Restricted portal verification | C10: Manual browser review | D10: Verified additions | E10: Portal search/CAPTCHA | F10: Weekly or as needed | G10: Manual
A11: 7 | B11: Distribute daily summary | C11: Email/cloud storage | D11: Daily digest and updated workbook | E11: Configure destination | F11: Daily | G11: Not configured
A13: Daily Active-Record Rule | B13: Logic | C13: Result
A14: Notification date | B14: Capture from first official tender publication | C14: Stored in Master Tenders
A15: Corrigendum | B15: Update same tender row; append dates/details | C15: No separate corrigendum sheet
A16: Closed status | B16: Remove from Master on scan date | C16: Logged in Exclusion Log
A17: Expired deadline | B17: Remove unless a verified extension/corrigendum keeps it open | C17: Logged in Exclusion Log
A18: Audit history | B18: Change remains in Tender History / Writeback Audit | C18: No loss of change trace

Sheet Repository Setup
A1: V12 GitHub Automation Setup
A3: Upload the complete V12 repository package. GitHub Actions will scan sources, apply scope rules, update the workbook, create logs and commit the latest workbook.
A5: Step | B5: Action | C5: GitHub Location | D5: Result
A6: 1 | B6: Upload all files and folders from the V12 ZIP | C6: Repository root | D6: Complete application available
A7: 2 | B7: Enable Actions | C7: Repository > Actions | D7: Scheduled runner enabled
A8: 3 | B8: Allow workflow write permission | C8: Settings > Actions > General | D8: Workflow can commit updated workbook
A9: 4 | B9: Run the workflow manually once | C9: Actions > Daily Renewable Tender Update | D9: Initial validation run
A10: 5 | B10: Review the workflow summary and logs | C10: Actions run page | D10: Errors and scan coverage visible
A11: 6 | B11: Download or open latest workbook | C11: Output/Renewable_Tender_Tracker_V12.xlsx | D11: Latest active tender tracker
A12: 7 | B12: Edit agency/source configuration as required | C12: Config/agencies.json | D12: Expanded or corrected source coverage
A13: 8 | B13: Edit scope rules only when needed | C13: Config/scope_rules.json | D13: Eligibility criteria updated
A14: 9 | B14: Restricted/CAPTCHA portals | C14: Manual Verification Queue | D14: Manual review remains visible
A15: 10 | B15: Do not upload only the workbook | C15: Repository root | D15: Scripts and workflow are required

Sheet Automation Status
A1: V12 Daily Automation Status
A4: Setting | B4: Configured Value | C4: Runtime Value | D4: Notes | F4: Run ID | G4: Started | H4: Finished | I4: Records Active | J4: Result
A5: Project Version | B5: 14.0
A6: Minimum Capacity MW | B6: 100 | D6: Tenders below 100 MW are excluded
A7: Exclude Rooftop | B7: Yes
A8: Exclude PM-KUSUM | B8: Yes
A9: Exclude EPC/Supply/Installation | B9: Daily 08:00 IST
A10: Remove Closed/Expired | B10: Yes
A11: Corrigendum Storage | B11: Same Master row
A12: Schedule | B12: Daily 08:00 IST | D12: 02:30 UTC
A13: Last Successful Run | C13: 46315.34 | D13: Written by automation
A14: Last Run Result | C14: Success | D14: Written by automation
A15: Latest Workbook Commit | D15: Written by automation
F505: RUN-20260803061445 | G505: 46237.26 | H505: 46237.26 | I505: 7 | J505: Success
F506: RUN-20260804054821 | G506: 46238.242 | H506: 46238.242 | I506: 6 | J506: Success
F507: RUN-20260805054700 | G507: 46239.241 | H507: 46239.241 | I507: 6 | J507: Success
F508: RUN-20260806055010 | G508: 46240.243 | H508: 46240.243 | I508: 7 | J508: Success
F509: RUN-20260807045332 | G509: 46241.204 | H509: 46241.204 | I509: 7 | J509: Success
F510: RUN-20260808040649 | G510: 46242.171 | H510: 46242.171 | I510: 6 | J510: Success
F511: RUN-20260809041441 | G511: 46243.177 | H511: 46243.177 | I511: 7 | J511: Success
F512: RUN-20260810043138 | G512: 46244.189 | H512: 46244.189 | I512: 7 | J512: Success
F513: RUN-20260811041724 | G513: 46245.179 | H513: 46245.179 | I513: 5 | J513: Success
F514: RUN-20260812043908 | G514: 46246.194 | H514: 46246.194 | I514: 5 | J514: Success
F515: RUN-20260813044143 | G515: 46247.196 | H515: 46247.196 | I515: 5 | J515: Success
F516: RUN-20260814043851 | G516: 46248.194 | H516: 46248.194 | I516: 5 | J516: Success
... F582: RUN-20261020080941 | G582: 46315.34 | H582: 46315.34 | I582: 12 | J582: Success

Sheet Connector Health
A1: V13 Dedicated Connector Health
A3: Each agency has its own connector module. Runtime health, extracted counts and failures are written by GitHub Actions.
A5: Category | B5: Agency | C5: Connector Module | D5: Source URL | E5: Connector Type | F5: Last Run | G5: Records Found | H5: Accepted | I5: Rejected | J5: Status | K5: Error / Notes
A6: Central | B6: SECI | C6: seci | D6: https://www.seci.co.in/tenders/ | E6: Dedicated HTML | G6: 0 | H6: 0 | I6: 0 | J6: Not Run
A7: Central | B7: NTPC REL | C7: ntpc_rel | D7: https://ntpctender.ntpc.co.in/Index/Search?Region=10&Type=Reg | E7: Dedicated HTML | G7: 0 | H7: 0 | I7: 0 | J7: Not Run
A8: Central | B8: NHPC | C8: nhpc | D8: https://www.nhpcindia.com/welcome/tender.html | E8: Dedicated HTML/PDF | G8: 0 | H8: 0 | I8: 0 | J8: Not Run
A9: Central | B9: SJVN | C9: sjvn | D9: https://sjvn.nic.in/en/tender | E9: Dedicated HTML/PDF | G9: 0 | H9: 0 | I9: 0 | J9: Not Run
A10: Central | B10: NLCIL | C10: nlcil | D10: https://www.nlcindia.in/ | E10: Dedicated HTML/PDF | G10: 0 | H10: 0 | I10: 0 | J10: Not Run
A11: Central | B11: GUVNL (ISTS) | C11: guvnl_ists | D11: https://www.guvnl.com/ | E11: Dedicated HTML/PDF | G11: 0 | H11: 0 | I11: 0 | J11: Not Run
A12: Central | B12: REMCL | C12: remcl | D12: https://www.remcl.in/ | E12: Dedicated HTML/PDF | G12: 0 | H12: 0 | I12: 0 | J12: Not Run
A13: Rajasthan | B13: RUVNL | C13: ruvnl | D13: https://eproc.rajasthan.gov.in/nicgep/app | E13: Portal connector | G13: 0 | H13: 0 | I13: 0 | J13: Not Run
A14: Rajasthan | B14: RVPN | C14: rvpn | D14: https://energy.rajasthan.gov.in/rvpnl | E14: Dedicated HTML/Portal | G14: 0 | H14: 0 | I14: 0 | J14: Not Run
A15: Karnataka | B15: KREDL | C15: kredl | D15: https://kppp.karnataka.gov.in/ | E15: Portal connector | G15: 0 | H15: 0 | I15: 0 | J15: Not Run
A16: Karnataka | B16: KPTCL | C16: kptcl | D16: https://kptcl.karnataka.gov.in/ | E16: Dedicated HTML/Portal | G16: 0 | H16: 0 | I16: 0 | J16: Not Run
A17: Karnataka | B17: KPCL | C17: kpcl | D17: https://karnatakapower.com/ | E17: Dedicated HTML/Portal | G17: 0 | H17: 0 | I17: 0 | J17: Not Run
... A36: Bihar | B36: BSPHCL | C36: bsphcl | D36: https://www.bsphcl.co.in/ | E36: Dedicated HTML/Portal | G36: 0 | H36: 0 | I36: 0 | J36: Not Run

Sheet Clause Extraction QA
A1: V13 PLF and Supply-Clause Extraction Quality Review
A4: Extraction ID | B4: Tender ID | C4: Agency | D4: Field | E4: Extracted Value | F4: Unit | G4: Confidence % | H4: Evidence Snippet | I4: Source Document | J4: Page | K4: Review Decision | L4: Reviewer Notes

Sheet PLF Rule Library
A1: V13 PLF / CUF / Availability Rule Library
A4: Field | B4: Pattern Family | C4: Extraction Target | D4: Unit | E4: Priority | F4: Validation Range | G4: Applies To | H4: Notes
A5: Minimum Annual PLF | B5: annual + minimum + PLF | C5: Percentage | D5: % | E5: High | F5: 0–100 | G5: FDRE/RTC/thermal-backed RE | H5: Prefer explicit annual guarantee
A6: Minimum Monthly PLF | B6: monthly + minimum + PLF | C6: Percentage | D6: % | E6: High | F6: 0–100 | G6: FDRE/RTC | H6: Capture monthly guarantee separately
A7: Minimum CUF | B7: minimum + CUF | C7: Percentage | D7: % | E7: High | F7: 0–100 | G7: Solar/Wind/Hybrid | H7: Do not treat as PLF
A8: Declared CUF Range | B8: declared CUF / CUF range | C8: Lower and upper % | D8: % | E8: Medium | F8: 0–100 | G8: Solar/Wind/Hybrid | H8: Capture range and selected bid value
A9: Annual Availability | B9: annual availability | C9: Percentage | D9: % | E9: High | F9: 0–100 | G9: BESS/PSP | H9: PLF not applicable
A10: Monthly Availability | B10: monthly availability | C10: Percentage | D10: % | E10: High | F10: 0–100 | G10: BESS/PSP | H10: Capture payment-linked availability
A11: Peak Supply Obligation | B11: MWh per MW per day | C11: Energy obligation | D11: MWh/MW/day | E11: High | F11: >0 | G11: FDRE/BESS | H11: Capture dispatch window
A12: Allowed Shortfall | B12: shortfall up to / tolerance | C12: Percentage or energy | D12: % / MWh | E12: High | F12: >=0 | G12: All | H12: Link to penalty clause
A13: Under-Supply Penalty | B13: shortfall / under-supply + multiplier | C13: Formula/text | D13: Text | E13: High | F13: Non-empty | G13: All | H13: Store evidence snippet and page
A14: External Energy Cap | B14: green market / bilateral + up to | C14: Percentage | D14: % | E14: High | F14: 0–100 | G14: FDRE/RTC | H14: Separate charging from direct supply
A16: Minimum Annual PLF | B16: not less than annual PLF / guaranteed PLF | C16: Percentage | D16: % | E16: High | F16: 0–100 | G16: FDRE/RTC | H16: Handles shall be / at least / guaranteed
... A28: Merchant Sale Timing | B28: third-party or merchant sale after obligation | C28: Text | D28: Text | E28: Medium | F28: Non-empty | G28: FDRE/BESS | H28: Capture timing restriction

Sheet V14 Production Readiness
A1: V14 Production Readiness & Acceptance
A3: V14 is a clean repository release with corrected CI, stronger clause extraction, page-level evidence and connector acceptance controls.
A5: Control | B5: Purpose | C5: Pass Condition | D5: Runtime Evidence | E5: Owner | F5: Frequency | G5: Status | H5: Notes
A6: Unit tests | B6: Protect parser and filtering logic | C6: All tests pass | D6: GitHub Actions test log | E6: Maintainer | F6: Every push | G6: Configured
A7: Workflow syntax | B7: Prevent invalid YAML | C7: Workflow loads and job graph appears | D7: Actions run | E7: Maintainer | F7: Every change | G7: Configured
A8: Connector health | B8: Track source failures | C8: Each enabled connector reports status | D8: Logs/connector_health.json | E8: Maintainer | F8: Daily | G8: Configured
A9: Workbook safety | B9: Prevent data loss | C9: Backup before every live save | D9: backups/ folder | E9: Automation | F9: Daily | G9: Configured
A10: PLF evidence | B10: Avoid unsupported extraction | C10: Value + confidence + page snippet | D10: Clause Extraction QA | E10: Reviewer | F10: Per tender | G10: Configured
A11: No-inference policy | B11: Avoid fabricated commercial terms | C11: Missing clauses remain Not verified | D11: Master Tenders | E11: Reviewer | F11: Per tender | G11: Configured
A12: Closed removal | B12: Keep active list current | C12: Closed/expired removed from Master | D12: Exclusion Log | E12: Automation | F12: Daily | G12: Configured
A13: Portal acceptance | B13: Validate live selectors | C13: Expected official records returned | D13: Connector Health | E13: Maintainer | F13: Initial + after changes | G13: Pending live tests
